[{"Word":"abba","Syllables":["ab","ba"]},{"Word":"ackord","Syllables":["ack","ord"]},{"Word":"affär","Syllables":["af","fär"]},{"Word":"alltför","Syllables":["allt","för"]},{"Word":"alltså","Syllables":["allt","så"]},{"Word":"alldeles","Syllables":["all","de","les"]},{"Word":"allmän","Syllables":["all","män"]},{"Word":"allmänheten","Syllables":["all","män","he","ten"]},{"Word":"alltid","Syllables":["all","tid"]},{"Word":"allting","Syllables":["all","ting"]},{"Word":"allvar","Syllables":["all","var"]},{"Word":"aldrig","Syllables":["al","drig"]},{"Word":"alger","Syllables":["al","ger"]},{"Word":"alla","Syllables":["al","la"]},{"Word":"allihopa","Syllables":["al","li","ho","pa"]},{"Word":"alvedon","Syllables":["al","ve","don"]},{"Word":"andel","Syllables":["an","del"]},{"Word":"andetag","Syllables":["an","de","tag"]},{"Word":"andra","Syllables":["an","dra"]},{"Word":"ange","Syllables":["an","ge"]},{"Word":"anka","Syllables":["an","ka"]},{"Word":"anledningen","Syllables":["an","led","ning","en"]},{"Word":"anländer","Syllables":["an","län","der"]},{"Word":"anna","Syllables":["an","na"]},{"Word":"annan","Syllables":["an","nan"]},{"Word":"annanstans","Syllables":["an","nan","stans"]},{"Word":"annars","Syllables":["an","nars"]},{"Word":"annat","Syllables":["an","nat"]},{"Word":"annorlunda","Syllables":["an","nor","lun","da"]},{"Word":"ansats","Syllables":["an","sats"]},{"Word":"ansikte","Syllables":["an","sik","te"]},{"Word":"ansluta","Syllables":["an","slu","ta"]},{"Word":"antal","Syllables":["an","tal"]},{"Word":"anteckning","Syllables":["an","teck","ning"]},{"Word":"antingen","Syllables":["an","ting","en"]},{"Word":"användbar","Syllables":["an","vändb","ar"]},{"Word":"använda","Syllables":["an","vän","da"]},{"Word":"aphänder","Syllables":["ap","hän","der"]},{"Word":"applåderade","Syllables":["ap","plå","de","ra","de"]},{"Word":"arbetsdille","Syllables":["ar","bets","dil","le"]},{"Word":"arbete","Syllables":["ar","be","te"]},{"Word":"arja","Syllables":["ar","ja"]},{"Word":"armarna","Syllables":["ar","mar","na"]},{"Word":"armé","Syllables":["ar","mé"]},{"Word":"artister","Syllables":["ar","tis","ter"]},{"Word":"askan","Syllables":["as","kan"]},{"Word":"astaire","Syllables":["as","taire"]},{"Word":"autografer","Syllables":["au","to","gra","fer"]},{"Word":"avgaser","Syllables":["av","ga","ser"]},{"Word":"avlagd","Syllables":["av","lagd"]},{"Word":"avlägsen","Syllables":["av","läg","sen"]},{"Word":"avsats","Syllables":["av","sats"]},{"Word":"avstånd","Syllables":["av","stånd"]},{"Word":"ababwa","Syllables":["a","bab","wa"]},{"Word":"ade","Syllables":["a","de"]},{"Word":"adoption","Syllables":["a","dop","tion"]},{"Word":"alice","Syllables":["a","lice"]},{"Word":"alí","Syllables":["a","lí"]},{"Word":"anat","Syllables":["a","nat"]},{"Word":"aning","Syllables":["a","ning"]},{"Word":"apa","Syllables":["a","pa"]},{"Word":"apor","Syllables":["a","por"]},{"Word":"are","Syllables":["a","re"]},{"Word":"arenorna","Syllables":["a","re","nor","na"]},{"Word":"atombombsexplotion","Syllables":["a","tom","bombs","ex","plo","tion"]},{"Word":"atomen","Syllables":["a","to","men"]},{"Word":"babwa","Syllables":["bab","wa"]},{"Word":"baddar","Syllables":["bad","dar"]},{"Word":"balkongen","Syllables":["bal","kong","en"]},{"Word":"bankar","Syllables":["bank","ar"]},{"Word":"banna","Syllables":["ban","na"]},{"Word":"banne","Syllables":["ban","ne"]},{"Word":"barfota","Syllables":["bar","fota"]},{"Word":"barnet","Syllables":["bar","net"]},{"Word":"baudelaire","Syllables":["bau","de","laire"]},{"Word":"bada","Syllables":["ba","da"]},{"Word":"badar","Syllables":["ba","dar"]},{"Word":"bade","Syllables":["ba","de"]},{"Word":"badi","Syllables":["ba","di"]},{"Word":"badiba","Syllables":["ba","di","ba"]},{"Word":"bagare","Syllables":["ba","ga","re"]},{"Word":"bakom","Syllables":["ba","kom"]},{"Word":"balans","Syllables":["ba","lans"]},{"Word":"bana","Syllables":["ba","na"]},{"Word":"bara","Syllables":["ba","ra"]},{"Word":"baren","Syllables":["ba","ren"]},{"Word":"bergatroll","Syllables":["ber","ga","troll"]},{"Word":"bergatrollet","Syllables":["ber","ga","trol","let"]},{"Word":"betsel","Syllables":["bet","sel"]},{"Word":"bedrägeri","Syllables":["be","drä","ge","ri"]},{"Word":"befalla","Syllables":["be","fal","la"]},{"Word":"befolka","Syllables":["be","fol","ka"]},{"Word":"begrepp","Syllables":["be","grepp"]},{"Word":"behärskar","Syllables":["be","härs","kar"]},{"Word":"behövde","Syllables":["be","höv","de"]},{"Word":"behöver","Syllables":["be","hö","ver"]},{"Word":"bekant","Syllables":["be","kant"]},{"Word":"belönas","Syllables":["be","lö","nas"]},{"Word":"benen","Syllables":["be","nen"]},{"Word":"bero","Syllables":["be","ro"]},{"Word":"berusning","Syllables":["be","rus","ning"]},{"Word":"berätta","Syllables":["be","rät","ta"]},{"Word":"berättelse","Syllables":["be","rät","tel","se"]},{"Word":"berömmelsen","Syllables":["be","röm","mel","sen"]},{"Word":"berörd","Syllables":["be","rörd"]},{"Word":"beröra","Syllables":["be","rö","ra"]},{"Word":"beskriva","Syllables":["be","skri","va"]},{"Word":"beslagtog","Syllables":["be","slag","tog"]},{"Word":"beslut","Syllables":["be","slut"]},{"Word":"besluta","Syllables":["be","slu","ta"]},{"Word":"beslutet","Syllables":["be","slu","tet"]},{"Word":"beställer","Syllables":["be","stäl","ler"]},{"Word":"bestämma","Syllables":["be","stäm","ma"]},{"Word":"bestämmer","Syllables":["be","stäm","mer"]},{"Word":"besvär","Syllables":["be","svär"]},{"Word":"besök","Syllables":["be","sök"]},{"Word":"betala","Syllables":["be","ta","la"]},{"Word":"betyda","Syllables":["be","ty","da"]},{"Word":"betyder","Syllables":["be","ty","der"]},{"Word":"bevisa","Syllables":["be","vi","sa"]},{"Word":"bevisat","Syllables":["be","vi","sat"]},{"Word":"beväpnar","Syllables":["be","väp","nar"]},{"Word":"bidubidubi","Syllables":["bidu","bi","du","bi"]},{"Word":"bildar","Syllables":["bil","dar"]},{"Word":"bilden","Syllables":["bil","den"]},{"Word":"bilder","Syllables":["bil","der"]},{"Word":"bilderna","Syllables":["bil","der","na"]},{"Word":"biljett","Syllables":["bil","jett"]},{"Word":"bindefeldt","Syllables":["bin","de","feldt"]},{"Word":"bittida","Syllables":["bit","ti","da"]},{"Word":"bidragstagaren","Syllables":["bi","drags","ta","ga","ren"]},{"Word":"bio","Syllables":["bi","o"]},{"Word":"biologi","Syllables":["bi","o","lo","gi"]},{"Word":"bita","Syllables":["bi","ta"]},{"Word":"bitars","Syllables":["bi","tars"]},{"Word":"bjuda","Syllables":["bju","da"]},{"Word":"bjuder","Syllables":["bju","der"]},{"Word":"blanda","Syllables":["blan","da"]},{"Word":"blandades","Syllables":["blan","da","des"]},{"Word":"bleka","Syllables":["ble","ka"]},{"Word":"blicken","Syllables":["blick","en"]},{"Word":"blivit","Syllables":["bli","vit"]},{"Word":"blocket","Syllables":["block","et"]},{"Word":"blomma","Syllables":["blom","ma"]},{"Word":"blommar","Syllables":["blom","mar"]},{"Word":"blommor","Syllables":["blom","mor"]},{"Word":"blommorna","Syllables":["blom","mor","na"]},{"Word":"blonda","Syllables":["blon","da"]},{"Word":"blodet","Syllables":["blo","det"]},{"Word":"blundar","Syllables":["blun","dar"]},{"Word":"blåsa","Syllables":["blå","sa"]},{"Word":"blåser","Syllables":["blå","ser"]},{"Word":"blåsut","Syllables":["blå","sut"]},{"Word":"blåval","Syllables":["blå","val"]},{"Word":"blåögd","Syllables":["blå","ögd"]},{"Word":"bodde","Syllables":["bod","de"]},{"Word":"bojdading","Syllables":["boj","da","ding"]},{"Word":"bokstav","Syllables":["bok","stav"]},{"Word":"bonden","Syllables":["bon","den"]},{"Word":"borsta","Syllables":["bors","ta"]},{"Word":"borde","Syllables":["bor","de"]},{"Word":"bordet","Syllables":["bor","det"]},{"Word":"borta","Syllables":["bor","ta"]},{"Word":"bortom","Syllables":["bor","tom"]},{"Word":"botten","Syllables":["bot","ten"]},{"Word":"boken","Syllables":["bo","ken"]},{"Word":"bomull","Syllables":["bo","mull"]},{"Word":"branten","Syllables":["bran","ten"]},{"Word":"brassband","Syllables":["brass","band"]},{"Word":"bredvid","Syllables":["bred","vid"]},{"Word":"bringa","Syllables":["bring","a"]},{"Word":"bringas","Syllables":["bring","as"]},{"Word":"brinner","Syllables":["brin","ner"]},{"Word":"brister","Syllables":["bris","ter"]},{"Word":"broarna","Syllables":["bro","ar","na"]},{"Word":"brunbrända","Syllables":["brun","brän","da"]},{"Word":"brukar","Syllables":["bru","kar"]},{"Word":"bruno","Syllables":["bru","no"]},{"Word":"bryggan","Syllables":["bryg","gan"]},{"Word":"bryta","Syllables":["bry","ta"]},{"Word":"bryter","Syllables":["bry","ter"]},{"Word":"bränna","Syllables":["brän","na"]},{"Word":"bränner","Syllables":["brän","ner"]},{"Word":"bråka","Syllables":["brå","ka"]},{"Word":"buller","Syllables":["bul","ler"]},{"Word":"bunden","Syllables":["bun","den"]},{"Word":"bundit","Syllables":["bun","dit"]},{"Word":"bugar","Syllables":["bu","gar"]},{"Word":"buren","Syllables":["bu","ren"]},{"Word":"butik","Syllables":["bu","tik"]},{"Word":"bygga","Syllables":["byg","ga"]},{"Word":"bygger","Syllables":["byg","ger"]},{"Word":"byta","Syllables":["by","ta"]},{"Word":"bytas","Syllables":["by","tas"]},{"Word":"bästa","Syllables":["bäs","ta"]},{"Word":"bättre","Syllables":["bät","tre"]},{"Word":"bära","Syllables":["bä","ra"]},{"Word":"båda","Syllables":["bå","da"]},{"Word":"både","Syllables":["bå","de"]},{"Word":"böcker","Syllables":["böck","er"]},{"Word":"börja","Syllables":["bör","ja"]},{"Word":"börjar","Syllables":["bör","jar"]},{"Word":"började","Syllables":["bör","ja","de"]},{"Word":"böja","Syllables":["bö","ja"]},{"Word":"café","Syllables":["ca","fé"]},{"Word":"camilla","Syllables":["ca","mil","la"]},{"Word":"caramelldansen","Syllables":["ca","ra","mell","dan","sen"]},{"Word":"carolus","Syllables":["ca","ro","lus"]},{"Word":"casimir","Syllables":["ca","si","mir"]},{"Word":"centrum","Syllables":["cen","trum"]},{"Word":"ceremoni","Syllables":["ce","re","mo","ni"]},{"Word":"chansen","Syllables":["chan","sen"]},{"Word":"chanser","Syllables":["chan","ser"]},{"Word":"christer","Syllables":["chris","ter"]},{"Word":"cirka","Syllables":["cir","ka"]},{"Word":"cirkel","Syllables":["cir","kel"]},{"Word":"citaten","Syllables":["ci","ta","ten"]},{"Word":"coca","Syllables":["co","ca"]},{"Word":"cola","Syllables":["co","la"]},{"Word":"cykel","Syllables":["cy","kel"]},{"Word":"cykeltur","Syllables":["cy","kel","tur"]},{"Word":"damtidning","Syllables":["dam","tid","ning"]},{"Word":"dangdang","Syllables":["dang","dang"]},{"Word":"dansa","Syllables":["dan","sa"]},{"Word":"dansar","Syllables":["dan","sar"]},{"Word":"danvikstull","Syllables":["dan","viks","tull"]},{"Word":"darling","Syllables":["dar","ling"]},{"Word":"dagen","Syllables":["da","gen"]},{"Word":"damen","Syllables":["da","men"]},{"Word":"delning","Syllables":["del","ning"]},{"Word":"denna","Syllables":["den","na"]},{"Word":"dessa","Syllables":["des","sa"]},{"Word":"detta","Syllables":["det","ta"]},{"Word":"debitera","Syllables":["de","bi","te","ra"]},{"Word":"decimala","Syllables":["de","ci","ma","la"]},{"Word":"dela","Syllables":["de","la"]},{"Word":"delas","Syllables":["de","las"]},{"Word":"delen","Syllables":["de","len"]},{"Word":"demonerna","Syllables":["de","mo","ner","na"]},{"Word":"deras","Syllables":["de","ras"]},{"Word":"dimman","Syllables":["dim","man"]},{"Word":"diskussion","Syllables":["dis","kus","sion"]},{"Word":"diskutera","Syllables":["dis","ku","te","ra"]},{"Word":"diagram","Syllables":["di","a","gram"]},{"Word":"dialog","Syllables":["di","a","log"]},{"Word":"diamant","Syllables":["di","a","mant"]},{"Word":"dina","Syllables":["di","na"]},{"Word":"dinosaurie","Syllables":["di","no","sau","ri","e"]},{"Word":"direkt","Syllables":["di","rekt"]},{"Word":"direktsänds","Syllables":["di","rekt","sänds"]},{"Word":"direktiv","Syllables":["di","rek","tiv"]},{"Word":"disträheten","Syllables":["di","strä","he","ten"]},{"Word":"divide","Syllables":["di","vi","de"]},{"Word":"djursholm","Syllables":["djurs","holm"]},{"Word":"djupa","Syllables":["dju","pa"]},{"Word":"djävulens","Syllables":["djä","vu","lens"]},{"Word":"doftar","Syllables":["dof","tar"]},{"Word":"doften","Syllables":["dof","ten"]},{"Word":"dollarn","Syllables":["dol","larn"]},{"Word":"dragspel","Syllables":["drag","spel"]},{"Word":"droppe","Syllables":["drop","pe"]},{"Word":"drunknar","Syllables":["drunk","nar"]},{"Word":"dränker","Syllables":["drän","ker"]},{"Word":"dräper","Syllables":["drä","per"]},{"Word":"drömde","Syllables":["dröm","de"]},{"Word":"drömma","Syllables":["dröm","ma"]},{"Word":"drömmar","Syllables":["dröm","mar"]},{"Word":"drömmarna","Syllables":["dröm","mar","na"]},{"Word":"drömmer","Syllables":["dröm","mer"]},{"Word":"dröjer","Syllables":["drö","jer"]},{"Word":"dubbel","Syllables":["dub","bel"]},{"Word":"dudi","Syllables":["du","di"]},{"Word":"dupera","Syllables":["du","pe","ra"]},{"Word":"dyra","Syllables":["dy","ra"]},{"Word":"däcket","Syllables":["däck","et"]},{"Word":"därför","Syllables":["där","för"]},{"Word":"därpå","Syllables":["där","på"]},{"Word":"därvid","Syllables":["där","vid"]},{"Word":"därifrån","Syllables":["dä","ri","från"]},{"Word":"därute","Syllables":["dä","ru","te"]},{"Word":"dålig","Syllables":["dål","ig"]},{"Word":"dålig","Syllables":["då","lig"]},{"Word":"dånar","Syllables":["då","nar"]},{"Word":"dörrar","Syllables":["dör","rar"]},{"Word":"dörren","Syllables":["dör","ren"]},{"Word":"döda","Syllables":["dö","da"]},{"Word":"düsseldorf","Syllables":["düs","sel","dorf"]},{"Word":"dj","Syllables":["d","j"]},{"Word":"ebbat","Syllables":["eb","bat"]},{"Word":"effekt","Syllables":["ef","fekt"]},{"Word":"efter","Syllables":["ef","ter"]},{"Word":"elden","Syllables":["el","den"]},{"Word":"eller","Syllables":["el","ler"]},{"Word":"elvispojkarna","Syllables":["el","vis","poj","kar","na"]},{"Word":"elände","Syllables":["el","än","de"]},{"Word":"engberg","Syllables":["eng","berg"]},{"Word":"enda","Syllables":["en","da"]},{"Word":"endast","Syllables":["en","dast"]},{"Word":"enhet","Syllables":["en","het"]},{"Word":"enkel","Syllables":["en","kel"]},{"Word":"enligt","Syllables":["en","ligt"]},{"Word":"ensam","Syllables":["en","sam"]},{"Word":"ensamhet","Syllables":["en","sam","het"]},{"Word":"ensamma","Syllables":["en","sam","ma"]},{"Word":"enslighet","Syllables":["en","slig","het"]},{"Word":"erbjudandet","Syllables":["er","bju","dan","det"]},{"Word":"erfarenhet","Syllables":["er","fa","ren","het"]},{"Word":"europa","Syllables":["eu","ropa"]},{"Word":"exakt","Syllables":["ex","akt"]},{"Word":"exakta","Syllables":["ex","ak","ta"]},{"Word":"exalterad","Syllables":["ex","al","te","rad"]},{"Word":"excitera","Syllables":["ex","ci","te","ra"]},{"Word":"exemplaren","Syllables":["ex","emp","la","ren"]},{"Word":"exempel","Syllables":["ex","em","pel"]},{"Word":"exotiska","Syllables":["ex","o","tis","ka"]},{"Word":"experiment","Syllables":["ex","pe","ri","ment"]},{"Word":"eder","Syllables":["e","der"]},{"Word":"egen","Syllables":["e","gen"]},{"Word":"egenskap","Syllables":["e","gen","skap"]},{"Word":"ekar","Syllables":["e","kar"]},{"Word":"elektrisk","Syllables":["e","lek","trisk"]},{"Word":"elefanterna","Syllables":["e","le","fan","ter","na"]},{"Word":"elementet","Syllables":["e","le","men","tet"]},{"Word":"eloise","Syllables":["e","lo","ise"]},{"Word":"eländig","Syllables":["e","län","dig"]},{"Word":"emilio","Syllables":["e","mi","li","o"]},{"Word":"emot","Syllables":["e","mot"]},{"Word":"enas","Syllables":["e","nas"]},{"Word":"energi","Syllables":["e","ner","gi"]},{"Word":"enormt","Syllables":["e","normt"]},{"Word":"era","Syllables":["e","ra"]},{"Word":"eric","Syllables":["e","ric"]},{"Word":"faktiskt","Syllables":["fak","tiskt"]},{"Word":"faktum","Syllables":["fak","tum"]},{"Word":"falla","Syllables":["fal","la"]},{"Word":"faller","Syllables":["fal","ler"]},{"Word":"falskeliger","Syllables":["fal","ske","li","ger"]},{"Word":"fanfar","Syllables":["fan","far"]},{"Word":"fantastisk","Syllables":["fan","tas","tisk"]},{"Word":"fantasi","Syllables":["fan","ta","si"]},{"Word":"fantasier","Syllables":["fan","ta","si","er"]},{"Word":"farliga","Syllables":["far","li","ga"]},{"Word":"fatta","Syllables":["fat","ta"]},{"Word":"fattar","Syllables":["fat","tar"]},{"Word":"fattiga","Syllables":["fat","ti","ga"]},{"Word":"fager","Syllables":["fa","ger"]},{"Word":"fakirer","Syllables":["fa","ki","rer"]},{"Word":"familj","Syllables":["fa","milj"]},{"Word":"familjelyckan","Syllables":["fa","mil","je","lyck","an"]},{"Word":"fara","Syllables":["fa","ra"]},{"Word":"faten","Syllables":["fa","ten"]},{"Word":"femtitre","Syllables":["fem","ti","tre"]},{"Word":"festen","Syllables":["fes","ten"]},{"Word":"fester","Syllables":["fes","ter"]},{"Word":"feber","Syllables":["fe","ber"]},{"Word":"fenix","Syllables":["fe","nix"]},{"Word":"fickan","Syllables":["fick","an"]},{"Word":"fimpar","Syllables":["fim","par"]},{"Word":"finger","Syllables":["fing","er"]},{"Word":"fingrar","Syllables":["fing","rar"]},{"Word":"finnas","Syllables":["fin","nas"]},{"Word":"finska","Syllables":["fin","ska"]},{"Word":"fiende","Syllables":["fi","en","de"]},{"Word":"fienden","Syllables":["fi","en","den"]},{"Word":"figur","Syllables":["fi","gur"]},{"Word":"fina","Syllables":["fi","na"]},{"Word":"fjuttig","Syllables":["fjut","tig"]},{"Word":"fjäder","Syllables":["fjä","der"]},{"Word":"flammor","Syllables":["flam","mor"]},{"Word":"flaskor","Syllables":["flas","kor"]},{"Word":"flera","Syllables":["fle","ra"]},{"Word":"flicka","Syllables":["flick","a"]},{"Word":"flipperspel","Syllables":["flip","per","spel"]},{"Word":"flunsan","Syllables":["flun","san"]},{"Word":"flygfärd","Syllables":["flyg","färd"]},{"Word":"flygplan","Syllables":["flyg","plan"]},{"Word":"flygplats","Syllables":["flyg","plats"]},{"Word":"flygtur","Syllables":["flyg","tur"]},{"Word":"flytta","Syllables":["flyt","ta"]},{"Word":"flyttade","Syllables":["flyt","ta","de"]},{"Word":"flyga","Syllables":["fly","ga"]},{"Word":"flyger","Syllables":["fly","ger"]},{"Word":"fläskig","Syllables":["fläs","kig"]},{"Word":"flödar","Syllables":["flö","dar"]},{"Word":"flöde","Syllables":["flö","de"]},{"Word":"foglarna","Syllables":["fog","lar","na"]},{"Word":"forskar","Syllables":["fors","kar"]},{"Word":"fortfarande","Syllables":["fort","fa","ran","de"]},{"Word":"fortsätta","Syllables":["fort","sät","ta"]},{"Word":"fortsätter","Syllables":["fort","sät","ter"]},{"Word":"formulär","Syllables":["for","mu","lär"]},{"Word":"fosterland","Syllables":["fos","ter","land"]},{"Word":"fotboll","Syllables":["fot","boll"]},{"Word":"foder","Syllables":["fo","der"]},{"Word":"fotografer","Syllables":["fo","to","gra","fer"]},{"Word":"fotografi","Syllables":["fo","to","gra","fi"]},{"Word":"fraktion","Syllables":["frak","tion"]},{"Word":"framför","Syllables":["fram","för"]},{"Word":"framgång","Syllables":["fram","gång"]},{"Word":"framtid","Syllables":["fram","tid"]},{"Word":"framtiden","Syllables":["fram","ti","den"]},{"Word":"franska","Syllables":["fran","ska"]},{"Word":"framåt","Syllables":["fra","måt"]},{"Word":"frilla","Syllables":["fril","la"]},{"Word":"fria","Syllables":["fri","a"]},{"Word":"friade","Syllables":["fri","a","de"]},{"Word":"friheten","Syllables":["fri","he","ten"]},{"Word":"fryser","Syllables":["fry","ser"]},{"Word":"fräknar","Syllables":["fräk","nar"]},{"Word":"främmande","Syllables":["främ","man","de"]},{"Word":"främre","Syllables":["främ","re"]},{"Word":"fråga","Syllables":["frå","ga"]},{"Word":"fröken","Syllables":["frö","ken"]},{"Word":"fullständig","Syllables":["full","stän","dig"]},{"Word":"fullständigt","Syllables":["full","stän","digt"]},{"Word":"fulla","Syllables":["ful","la"]},{"Word":"fumlade","Syllables":["fum","la","de"]},{"Word":"fungera","Syllables":["fun","gera"]},{"Word":"funkar","Syllables":["fun","kar"]},{"Word":"funky","Syllables":["fun","ky"]},{"Word":"funnen","Syllables":["fun","nen"]},{"Word":"fula","Syllables":["fu","la"]},{"Word":"fylla","Syllables":["fyl","la"]},{"Word":"fyllot","Syllables":["fyl","lot"]},{"Word":"fyrtifem","Syllables":["fyr","ti","fem"]},{"Word":"fyrtiåtta","Syllables":["fyr","ti","åt","ta"]},{"Word":"fyra","Syllables":["fy","ra"]},{"Word":"fyrahundra","Syllables":["fy","ra","hun","dra"]},{"Word":"fäller","Syllables":["fäl","ler"]},{"Word":"fäste","Syllables":["fäs","te"]},{"Word":"fåglarna","Syllables":["fåg","lar","na"]},{"Word":"fånga","Syllables":["fång","a"]},{"Word":"fångad","Syllables":["fång","ad"]},{"Word":"fångar","Syllables":["fång","ar"]},{"Word":"fången","Syllables":["fång","en"]},{"Word":"fågel","Syllables":["få","gel"]},{"Word":"fågelunge","Syllables":["få","ge","lung","e"]},{"Word":"följa","Syllables":["föl","ja"]},{"Word":"följde","Syllables":["föl","jde"]},{"Word":"följer","Syllables":["föl","jer"]},{"Word":"fönster","Syllables":["föns","ter"]},{"Word":"fönstren","Syllables":["föns","tren"]},{"Word":"fönstret","Syllables":["föns","tret"]},{"Word":"fönster","Syllables":["fön","ster"]},{"Word":"förrgår","Syllables":["förr","går"]},{"Word":"förbannad","Syllables":["för","ban","nad"]},{"Word":"förbannelsen","Syllables":["för","ban","nel","sen"]},{"Word":"förbereda","Syllables":["för","be","re","da"]},{"Word":"förbi","Syllables":["för","bi"]},{"Word":"förbjudet","Syllables":["för","bju","det"]},{"Word":"förbli","Syllables":["för","bli"]},{"Word":"förflutna","Syllables":["för","flut","na"]},{"Word":"förförd","Syllables":["för","förd"]},{"Word":"förgås","Syllables":["för","gås"]},{"Word":"förhäxad","Syllables":["för","häx","ad"]},{"Word":"förhöra","Syllables":["för","hö","ra"]},{"Word":"förkastar","Syllables":["för","kas","tar"]},{"Word":"förklaras","Syllables":["för","kla","ras"]},{"Word":"förklädd","Syllables":["för","klädd"]},{"Word":"förkung","Syllables":["för","kung"]},{"Word":"förkylning","Syllables":["för","kyl","ning"]},{"Word":"förlora","Syllables":["för","lo","ra"]},{"Word":"förlorad","Syllables":["för","lo","rad"]},{"Word":"förlorat","Syllables":["för","lo","rat"]},{"Word":"förlåt","Syllables":["för","låt"]},{"Word":"förlåta","Syllables":["för","lå","ta"]},{"Word":"förlåtet","Syllables":["för","lå","tet"]},{"Word":"Förmåga","Syllables":["För","må","ga"]},{"Word":"förnedring","Syllables":["för","ned","ring"]},{"Word":"förnekar","Syllables":["för","ne","kar"]},{"Word":"förresten","Syllables":["för","res","ten"]},{"Word":"förrom","Syllables":["för","rom"]},{"Word":"försoning","Syllables":["för","so","ning"]},{"Word":"första","Syllables":["för","sta"]},{"Word":"förstod","Syllables":["för","stod"]},{"Word":"förstoringsglas","Syllables":["för","storingsglas"]},{"Word":"förstorat","Syllables":["för","sto","rat"]},{"Word":"förstå","Syllables":["för","stå"]},{"Word":"förstår","Syllables":["för","står"]},{"Word":"förstås","Syllables":["för","stås"]},{"Word":"förstört","Syllables":["för","stört"]},{"Word":"försvinna","Syllables":["för","svin","na"]},{"Word":"försvinner","Syllables":["för","svin","ner"]},{"Word":"försök","Syllables":["för","sök"]},{"Word":"försökt","Syllables":["för","sökt"]},{"Word":"försörjning","Syllables":["för","sörj","ning"]},{"Word":"försöka","Syllables":["för","sö","ka"]},{"Word":"försöker","Syllables":["för","sö","ker"]},{"Word":"förtio","Syllables":["för","ti","o"]},{"Word":"förtjust","Syllables":["för","tjust"]},{"Word":"förtrollad","Syllables":["för","trol","lad"]},{"Word":"förtröstan","Syllables":["för","trös","tan"]},{"Word":"förtära","Syllables":["för","tä","ra"]},{"Word":"förvandlats","Syllables":["för","vand","lats"]},{"Word":"förvirring","Syllables":["för","vir","ring"]},{"Word":"förvänta","Syllables":["för","vän","ta"]},{"Word":"fötter","Syllables":["föt","ter"]},{"Word":"födelsedagshotell","Syllables":["fö","del","se","dags","hotell"]},{"Word":"föder","Syllables":["fö","der"]},{"Word":"föra","Syllables":["fö","ra"]},{"Word":"före","Syllables":["fö","re"]},{"Word":"föreliggande","Syllables":["fö","re","lig","gan","de"]},{"Word":"förenade","Syllables":["fö","re","na","de"]},{"Word":"föreslår","Syllables":["fö","re","slår"]},{"Word":"föreställa sig","Syllables":["fö","re","stäl","la sig"]},{"Word":"företaget","Syllables":["fö","re","ta","get"]},{"Word":"förevigt","Syllables":["fö","re","vigt"]},{"Word":"förut","Syllables":["fö","rut"]},{"Word":"förälder","Syllables":["fö","räl","der"]},{"Word":"förändrad","Syllables":["fö","ränd","rad"]},{"Word":"förändrats","Syllables":["fö","ränd","rats"]},{"Word":"förändring","Syllables":["fö","ränd","ring"]},{"Word":"gamla","Syllables":["gam","la"]},{"Word":"gammal","Syllables":["gam","mal"]},{"Word":"ganska","Syllables":["gans","ka"]},{"Word":"ganska","Syllables":["gan","ska"]},{"Word":"gardin","Syllables":["gar","din"]},{"Word":"gatlampa","Syllables":["gat","lam","pa"]},{"Word":"gata","Syllables":["ga","ta"]},{"Word":"gatan","Syllables":["ga","tan"]},{"Word":"gatans","Syllables":["ga","tans"]},{"Word":"gatorna","Syllables":["ga","tor","na"]},{"Word":"gerna","Syllables":["ger","na"]},{"Word":"gemensam","Syllables":["ge","men","sam"]},{"Word":"genom","Syllables":["ge","nom"]},{"Word":"genomblöt","Syllables":["ge","nom","blöt"]},{"Word":"genomskåda","Syllables":["ge","nom","skå","da"]},{"Word":"gillar","Syllables":["gil","lar"]},{"Word":"gissa","Syllables":["gis","sa"]},{"Word":"gifva","Syllables":["gi","fva"]},{"Word":"givet","Syllables":["gi","vet"]},{"Word":"givit","Syllables":["gi","vit"]},{"Word":"gjorde","Syllables":["gjor","de"]},{"Word":"glassbåt","Syllables":["glass","båt"]},{"Word":"glaciär","Syllables":["gla","ci","är"]},{"Word":"glada","Syllables":["gla","da"]},{"Word":"glida","Syllables":["gli","da"]},{"Word":"gloria","Syllables":["glo","ri","a"]},{"Word":"glädje","Syllables":["gläd","je"]},{"Word":"glömma","Syllables":["glöm","ma"]},{"Word":"glömmer","Syllables":["glöm","mer"]},{"Word":"gnista","Syllables":["gnis","ta"]},{"Word":"gnistrar","Syllables":["gnis","trar"]},{"Word":"gnida","Syllables":["gni","da"]},{"Word":"golvet","Syllables":["gol","vet"]},{"Word":"goda","Syllables":["go","da"]},{"Word":"godisbjörn","Syllables":["go","dis","björn"]},{"Word":"granne","Syllables":["gran","ne"]},{"Word":"graderna","Syllables":["gra","der","na"]},{"Word":"gratis","Syllables":["gra","tis"]},{"Word":"gravid","Syllables":["gra","vid"]},{"Word":"grenen","Syllables":["gre","nen"]},{"Word":"grubblade","Syllables":["grub","bla","de"]},{"Word":"grundläggande","Syllables":["grund","läg","gan","de"]},{"Word":"gruva","Syllables":["gru","va"]},{"Word":"gryningen","Syllables":["gry","ning","en"]},{"Word":"gränsen","Syllables":["grän","sen"]},{"Word":"gränser","Syllables":["grän","ser"]},{"Word":"gräshopporna","Syllables":["gräs","hop","por","na"]},{"Word":"gräset","Syllables":["grä","set"]},{"Word":"gråta","Syllables":["grå","ta"]},{"Word":"gråter","Syllables":["grå","ter"]},{"Word":"grönbruna","Syllables":["grön","bru","na"]},{"Word":"gröda","Syllables":["grö","da"]},{"Word":"gröna","Syllables":["grö","na"]},{"Word":"guidad","Syllables":["gui","dad"]},{"Word":"guldbyxorna","Syllables":["guld","byx","or","na"]},{"Word":"gullig","Syllables":["gul","lig"]},{"Word":"gummi","Syllables":["gum","mi"]},{"Word":"gummibjörn","Syllables":["gum","mi","björn"]},{"Word":"gudarna","Syllables":["gu","dar","na"]},{"Word":"gymmet","Syllables":["gym","met"]},{"Word":"gynna","Syllables":["gyn","na"]},{"Word":"gärna","Syllables":["gär","na"]},{"Word":"gånger","Syllables":["gång","er"]},{"Word":"gömmer","Syllables":["göm","mer"]},{"Word":"gömmor","Syllables":["göm","mor"]},{"Word":"göra","Syllables":["gö","ra"]},{"Word":"halvmesyrer","Syllables":["halv","me","sy","rer"]},{"Word":"halka","Syllables":["hal","ka"]},{"Word":"haller","Syllables":["hal","ler"]},{"Word":"halva","Syllables":["hal","va"]},{"Word":"hamnar","Syllables":["ham","nar"]},{"Word":"hamnat","Syllables":["ham","nat"]},{"Word":"handling","Syllables":["hand","ling"]},{"Word":"handel","Syllables":["han","del"]},{"Word":"handikapp","Syllables":["han","di","kapp"]},{"Word":"hastighet","Syllables":["has","tig","het"]},{"Word":"hatten","Syllables":["hat","ten"]},{"Word":"hade","Syllables":["ha","de"]},{"Word":"hadig","Syllables":["ha","dig"]},{"Word":"hatat","Syllables":["ha","tat"]},{"Word":"havet","Syllables":["ha","vet"]},{"Word":"hellre","Syllables":["hell","re"]},{"Word":"helgen","Syllables":["hel","gen"]},{"Word":"heller","Syllables":["hel","ler"]},{"Word":"helvete","Syllables":["hel","ve","te"]},{"Word":"hembyggd","Syllables":["hem","byggd"]},{"Word":"hemlighet","Syllables":["hem","lig","het"]},{"Word":"hemma","Syllables":["hem","ma"]},{"Word":"hemmaspa","Syllables":["hem","ma","spa"]},{"Word":"henne","Syllables":["hen","ne"]},{"Word":"hennes","Syllables":["hen","nes"]},{"Word":"henning","Syllables":["hen","ning"]},{"Word":"herdarnas","Syllables":["her","dar","nas"]},{"Word":"herre","Syllables":["her","re"]},{"Word":"hetta","Syllables":["het","ta"]},{"Word":"heja","Syllables":["he","ja"]},{"Word":"hela","Syllables":["he","la"]},{"Word":"heter","Syllables":["he","ter"]},{"Word":"himlen","Syllables":["him","len"]},{"Word":"himmel","Syllables":["him","mel"]},{"Word":"himmelsblå","Syllables":["him","mels","blå"]},{"Word":"himmelska","Syllables":["him","mel","ska"]},{"Word":"himmelen","Syllables":["him","me","len"]},{"Word":"hinder","Syllables":["hin","der"]},{"Word":"hindra","Syllables":["hin","dra"]},{"Word":"historia","Syllables":["his","to","ria"]},{"Word":"historia","Syllables":["his","to","ri","a"]},{"Word":"hitta","Syllables":["hit","ta"]},{"Word":"hittar","Syllables":["hit","tar"]},{"Word":"hittat","Syllables":["hit","tat"]},{"Word":"hjälplöst","Syllables":["hjälp","löst"]},{"Word":"hjälplösa","Syllables":["hjälp","lö","sa"]},{"Word":"hjälpa","Syllables":["hjäl","pa"]},{"Word":"hjälte","Syllables":["hjäl","te"]},{"Word":"hjärta","Syllables":["hjär","ta"]},{"Word":"hjärtas","Syllables":["hjär","tas"]},{"Word":"hjärtat","Syllables":["hjär","tat"]},{"Word":"honvid","Syllables":["hon","vid"]},{"Word":"hopplöst","Syllables":["hopp","löst"]},{"Word":"hoppa","Syllables":["hop","pa"]},{"Word":"hoppar","Syllables":["hop","par"]},{"Word":"hoppas","Syllables":["hop","pas"]},{"Word":"holiday","Syllables":["ho","li","day"]},{"Word":"honom","Syllables":["ho","nom"]},{"Word":"hugga","Syllables":["hug","ga"]},{"Word":"hundra","Syllables":["hund","ra"]},{"Word":"hundradels","Syllables":["hund","ra","dels"]},{"Word":"hundratals","Syllables":["hund","ra","tals"]},{"Word":"hundra","Syllables":["hun","dra"]},{"Word":"hunnerna","Syllables":["hun","ner","na"]},{"Word":"humant","Syllables":["hu","mant"]},{"Word":"huruvida","Syllables":["hu","ru","vi","da"]},{"Word":"husen","Syllables":["hu","sen"]},{"Word":"huset","Syllables":["hu","set"]},{"Word":"huvet","Syllables":["hu","vet"]},{"Word":"huvud","Syllables":["hu","vud"]},{"Word":"huvudvätning","Syllables":["hu","vud","vät","ning"]},{"Word":"huvudvätare","Syllables":["hu","vud","vä","ta","re"]},{"Word":"huv’et","Syllables":["hu","v’et"]},{"Word":"hyllning","Syllables":["hyll","ning"]},{"Word":"hälften","Syllables":["hälf","ten"]},{"Word":"hälsa","Syllables":["häl","sa"]},{"Word":"hänger","Syllables":["häng","er"]},{"Word":"hända","Syllables":["hän","da"]},{"Word":"hände","Syllables":["hän","de"]},{"Word":"händelse","Syllables":["hän","del","se"]},{"Word":"händer","Syllables":["hän","der"]},{"Word":"händerna","Syllables":["hän","der","na"]},{"Word":"härligheten","Syllables":["här","lig","he","ten"]},{"Word":"härliga","Syllables":["här","li","ga"]},{"Word":"härska","Syllables":["här","ska"]},{"Word":"härskar","Syllables":["här","skar"]},{"Word":"härifrån","Syllables":["hä","ri","från"]},{"Word":"hålla","Syllables":["hål","la"]},{"Word":"hårdhänt","Syllables":["hård","hänt"]},{"Word":"höfter","Syllables":["höf","ter"]},{"Word":"högmod","Syllables":["hög","mod"]},{"Word":"högrepris","Syllables":["hög","rep","ris"]},{"Word":"höjningen","Syllables":["höj","ning","en"]},{"Word":"hörde","Syllables":["hör","de"]},{"Word":"hösten","Syllables":["hös","ten"]},{"Word":"höga","Syllables":["hö","ga"]},{"Word":"höger","Syllables":["hö","ger"]},{"Word":"höja","Syllables":["hö","ja"]},{"Word":"höra","Syllables":["hö","ra"]},{"Word":"illa","Syllables":["il","la"]},{"Word":"ilska","Syllables":["il","ska"]},{"Word":"inga","Syllables":["ing","a"]},{"Word":"ingen","Syllables":["ing","en"]},{"Word":"ingenstans","Syllables":["ing","en","stans"]},{"Word":"ingenting","Syllables":["ing","en","ting"]},{"Word":"inget","Syllables":["ing","et"]},{"Word":"ingeting","Syllables":["ing","e","ting"]},{"Word":"indiehjärta","Syllables":["in","die","hjär","ta"]},{"Word":"indikerar","Syllables":["in","di","ke","rar"]},{"Word":"individ","Syllables":["in","di","vid"]},{"Word":"industrin","Syllables":["in","dus","trin"]},{"Word":"infektion","Syllables":["in","fek","tion"]},{"Word":"inflammerad","Syllables":["in","flam","me","rad"]},{"Word":"inför","Syllables":["in","för"]},{"Word":"inkluderar","Syllables":["in","klu","de","rar"]},{"Word":"innan","Syllables":["in","nan"]},{"Word":"inne","Syllables":["in","ne"]},{"Word":"innebar","Syllables":["in","ne","bar"]},{"Word":"innehålla","Syllables":["in","ne","hål","la"]},{"Word":"inre","Syllables":["in","re"]},{"Word":"inse","Syllables":["in","se"]},{"Word":"insekt","Syllables":["in","sekt"]},{"Word":"insekter","Syllables":["in","sek","ter"]},{"Word":"instrumentet","Syllables":["in","stru","men","tet"]},{"Word":"insåg","Syllables":["in","såg"]},{"Word":"inte","Syllables":["in","te"]},{"Word":"intervall","Syllables":["in","ter","vall"]},{"Word":"intressant","Syllables":["in","tres","sant"]},{"Word":"intresse","Syllables":["in","tres","se"]},{"Word":"inträffa","Syllables":["in","träf","fa"]},{"Word":"inägg","Syllables":["in","ägg"]},{"Word":"irrat","Syllables":["ir","rat"]},{"Word":"iskall","Syllables":["is","kall"]},{"Word":"istället","Syllables":["is","täl","let"]},{"Word":"ibland","Syllables":["i","bland"]},{"Word":"idag","Syllables":["i","dag"]},{"Word":"idé","Syllables":["i","dé"]},{"Word":"ifall","Syllables":["i","fall"]},{"Word":"ifeber","Syllables":["i","fe","ber"]},{"Word":"ifrån","Syllables":["i","från"]},{"Word":"ifrågasätt","Syllables":["i","frå","ga","sätt"]},{"Word":"igen","Syllables":["i","gen"]},{"Word":"igenom","Syllables":["i","ge","nom"]},{"Word":"igår","Syllables":["i","går"]},{"Word":"ihjäl","Syllables":["i","hjäl"]},{"Word":"ihop","Syllables":["i","hop"]},{"Word":"ihåg","Syllables":["i","håg"]},{"Word":"ikväll","Syllables":["i","kväll"]},{"Word":"imorgon","Syllables":["i","mor","gon"]},{"Word":"inom","Syllables":["i","nom"]},{"Word":"inombords","Syllables":["i","nom","bords"]},{"Word":"inuti","Syllables":["i","nu","ti"]},{"Word":"isolerat","Syllables":["i","so","le","rat"]},{"Word":"isär","Syllables":["i","sär"]},{"Word":"jakten","Syllables":["jak","ten"]},{"Word":"jannike","Syllables":["jan","ni","ke"]},{"Word":"jazzhuset","Syllables":["jazz","hu","set"]},{"Word":"jagad","Syllables":["ja","gad"]},{"Word":"jaja","Syllables":["ja","ja"]},{"Word":"jakobsberg","Syllables":["ja","kobs","berg"]},{"Word":"jonna","Syllables":["jon","na"]},{"Word":"jorden","Syllables":["jor","den"]},{"Word":"juveler","Syllables":["ju","ve","ler"]},{"Word":"jämföra","Syllables":["jäm","fö","ra"]},{"Word":"jämrar","Syllables":["jäm","rar"]},{"Word":"jättemycket","Syllables":["jät","te","myck","et"]},{"Word":"jävla","Syllables":["jäv","la"]},{"Word":"jävligaste","Syllables":["jäv","li","ga","ste"]},{"Word":"jäsa","Syllables":["jä","sa"]},{"Word":"jävel","Syllables":["jä","vel"]},{"Word":"kallas","Syllables":["kal","las"]},{"Word":"kamrater","Syllables":["kam","ra","ter"]},{"Word":"kanske","Syllables":["kan","ske"]},{"Word":"kanten","Syllables":["kan","ten"]},{"Word":"kappsäck","Syllables":["kapp","säck"]},{"Word":"kappa","Syllables":["kap","pa"]},{"Word":"kapten","Syllables":["kap","ten"]},{"Word":"karta","Syllables":["kar","ta"]},{"Word":"kasta","Syllables":["kas","ta"]},{"Word":"kastad","Syllables":["kas","tad"]},{"Word":"kastat","Syllables":["kas","tat"]},{"Word":"kameler","Syllables":["ka","me","ler"]},{"Word":"kanal","Syllables":["ka","nal"]},{"Word":"kanalen","Syllables":["ka","na","len"]},{"Word":"kanalerna","Syllables":["ka","na","ler","na"]},{"Word":"kanoner","Syllables":["ka","no","ner"]},{"Word":"kaos","Syllables":["ka","os"]},{"Word":"kapital","Syllables":["ka","pi","tal"]},{"Word":"karaktär","Syllables":["ka","rak","tär"]},{"Word":"karoliner","Syllables":["ka","ro","li","ner"]},{"Word":"kemi","Syllables":["ke","mi"]},{"Word":"kicka","Syllables":["kick","a"]},{"Word":"killar","Syllables":["kil","lar"]},{"Word":"killarna","Syllables":["kil","lar","na"]},{"Word":"kinden","Syllables":["kin","den"]},{"Word":"kittlar","Syllables":["kitt","lar"]},{"Word":"klamra","Syllables":["klam","ra"]},{"Word":"klappa","Syllables":["klap","pa"]},{"Word":"klassen","Syllables":["klas","sen"]},{"Word":"klagas","Syllables":["kla","gas"]},{"Word":"klara","Syllables":["kla","ra"]},{"Word":"klarar","Syllables":["kla","rar"]},{"Word":"klarat","Syllables":["kla","rat"]},{"Word":"klocka","Syllables":["klock","a"]},{"Word":"klockan","Syllables":["klock","an"]},{"Word":"klyschor","Syllables":["klysch","or"]},{"Word":"klänning","Syllables":["klän","ning"]},{"Word":"klättra","Syllables":["klät","tra"]},{"Word":"klättrar","Syllables":["klät","trar"]},{"Word":"kläder","Syllables":["klä","der"]},{"Word":"klöste","Syllables":["klös","te"]},{"Word":"knappar","Syllables":["knap","par"]},{"Word":"knivarna","Syllables":["kni","var","na"]},{"Word":"knockad","Syllables":["knock","ad"]},{"Word":"knoppen","Syllables":["knop","pen"]},{"Word":"knutna","Syllables":["knut","na"]},{"Word":"knäpper","Syllables":["knäp","per"]},{"Word":"kockar","Syllables":["kock","ar"]},{"Word":"kombinationen","Syllables":["kom","bi","na","tionen"]},{"Word":"komma","Syllables":["kom","ma"]},{"Word":"kommer","Syllables":["kom","mer"]},{"Word":"kommer inte","Syllables":["kom","mer in","te"]},{"Word":"kommit","Syllables":["kom","mit"]},{"Word":"konsonant","Syllables":["kon","so","nant"]},{"Word":"konstruktion","Syllables":["kon","struk","tion"]},{"Word":"kontinent","Syllables":["kon","ti","nent"]},{"Word":"kontor","Syllables":["kon","tor"]},{"Word":"kontroll","Syllables":["kon","troll"]},{"Word":"konverserade","Syllables":["kon","ver","se","ra","de"]},{"Word":"korrekt","Syllables":["kor","rekt"]},{"Word":"korridor","Syllables":["kor","ri","dor"]},{"Word":"korsa","Syllables":["kor","sa"]},{"Word":"kostnad","Syllables":["kost","nad"]},{"Word":"kosta","Syllables":["kos","ta"]},{"Word":"kotte","Syllables":["kot","te"]},{"Word":"kolonn","Syllables":["ko","lonn"]},{"Word":"koloni","Syllables":["ko","lo","ni"]},{"Word":"kopia","Syllables":["ko","pi","a"]},{"Word":"kostym","Syllables":["ko","stym"]},{"Word":"kraften","Syllables":["kraf","ten"]},{"Word":"krafter","Syllables":["kraf","ter"]},{"Word":"kraftiga","Syllables":["kraf","ti","ga"]},{"Word":"kragen","Syllables":["kra","gen"]},{"Word":"kredit","Syllables":["kre","dit"]},{"Word":"kristall","Syllables":["kris","tall"]},{"Word":"kristalliserar","Syllables":["kris","tal","li","se","rar"]},{"Word":"kristelig","Syllables":["kris","te","lig"]},{"Word":"krigets","Syllables":["kri","gets"]},{"Word":"kriminalisera","Syllables":["kri","mi","na","li","se","ra"]},{"Word":"kritiken","Syllables":["kri","ti","ken"]},{"Word":"kroppen","Syllables":["krop","pen"]},{"Word":"krossa","Syllables":["kros","sa"]},{"Word":"krossar","Syllables":["kros","sar"]},{"Word":"kronan","Syllables":["kro","nan"]},{"Word":"kroniskt","Syllables":["kro","ni","skt"]},{"Word":"kryper","Syllables":["kry","per"]},{"Word":"kräva","Syllables":["krä","va"]},{"Word":"kräver","Syllables":["krä","ver"]},{"Word":"krönas","Syllables":["krö","nas"]},{"Word":"kudden","Syllables":["kud","den"]},{"Word":"kulle","Syllables":["kul","le"]},{"Word":"kunde","Syllables":["kun","de"]},{"Word":"kunderna","Syllables":["kun","der","na"]},{"Word":"kunna","Syllables":["kun","na"]},{"Word":"kunnat","Syllables":["kun","nat"]},{"Word":"kunnen","Syllables":["kun","nen"]},{"Word":"kulorna","Syllables":["ku","lor","na"]},{"Word":"kura","Syllables":["ku","ra"]},{"Word":"kvadrat","Syllables":["kvad","rat"]},{"Word":"kvarter","Syllables":["kvar","ter"]},{"Word":"kvarteret","Syllables":["kvar","te","ret"]},{"Word":"kvinna","Syllables":["kvin","na"]},{"Word":"kvinnor","Syllables":["kvin","nor"]},{"Word":"kvinnornas","Syllables":["kvin","nor","nas"]},{"Word":"kvoten","Syllables":["kvo","ten"]},{"Word":"kvällen","Syllables":["kväl","len"]},{"Word":"kyrkan","Syllables":["kyr","kan"]},{"Word":"kysser","Syllables":["kys","ser"]},{"Word":"källar’n","Syllables":["käl","lar’n"]},{"Word":"kämpa","Syllables":["käm","pa"]},{"Word":"känslan","Syllables":["käns","lan"]},{"Word":"känslor","Syllables":["käns","lor"]},{"Word":"känslorna","Syllables":["käns","lor","na"]},{"Word":"kände","Syllables":["kän","de"]},{"Word":"känna","Syllables":["kän","na"]},{"Word":"känner","Syllables":["kän","ner"]},{"Word":"känsla","Syllables":["kän","sla"]},{"Word":"kärlek","Syllables":["kär","lek"]},{"Word":"kärlekshistoria","Syllables":["kär","leks","his","to","ri","a"]},{"Word":"kärleksparen","Syllables":["kär","leks","pa","ren"]},{"Word":"kärleken","Syllables":["kär","le","ken"]},{"Word":"kärlekens","Syllables":["kär","le","kens"]},{"Word":"käkar","Syllables":["kä","kar"]},{"Word":"kära","Syllables":["kä","ra"]},{"Word":"körberg","Syllables":["kör","berg"]},{"Word":"körde","Syllables":["kör","de"]},{"Word":"köpa","Syllables":["kö","pa"]},{"Word":"köper","Syllables":["kö","per"]},{"Word":"köra","Syllables":["kö","ra"]},{"Word":"lagra","Syllables":["lag","ra"]},{"Word":"lammkött","Syllables":["lamm","kött"]},{"Word":"lampan","Syllables":["lam","pan"]},{"Word":"landar","Syllables":["lan","dar"]},{"Word":"lastbil","Syllables":["last","bil"]},{"Word":"lady","Syllables":["la","dy"]},{"Word":"laga","Syllables":["la","ga"]},{"Word":"lagar","Syllables":["la","gar"]},{"Word":"lamor","Syllables":["la","mor"]},{"Word":"later","Syllables":["la","ter"]},{"Word":"lava","Syllables":["la","va"]},{"Word":"ledde","Syllables":["led","de"]},{"Word":"ledsna","Syllables":["led","sna"]},{"Word":"ledstjärnas","Syllables":["led","stjär","nas"]},{"Word":"leda","Syllables":["le","da"]},{"Word":"leendet","Syllables":["le","en","det"]},{"Word":"legend","Syllables":["le","gend"]},{"Word":"lejon","Syllables":["le","jon"]},{"Word":"leker","Syllables":["le","ker"]},{"Word":"lena","Syllables":["le","na"]},{"Word":"letat","Syllables":["le","tat"]},{"Word":"leva","Syllables":["le","va"]},{"Word":"levandeorkan","Syllables":["le","van","de","or","kan"]},{"Word":"lever","Syllables":["le","ver"]},{"Word":"ligga","Syllables":["lig","ga"]},{"Word":"ligger","Syllables":["lig","ger"]},{"Word":"liknande","Syllables":["lik","nan","de"]},{"Word":"liksom","Syllables":["lik","som"]},{"Word":"likställa","Syllables":["lik","stäl","la"]},{"Word":"likväl","Syllables":["lik","väl"]},{"Word":"lilla","Syllables":["lil","la"]},{"Word":"lindra","Syllables":["lin","dra"]},{"Word":"linje","Syllables":["lin","je"]},{"Word":"linjen","Syllables":["lin","jen"]},{"Word":"lista","Syllables":["lis","ta"]},{"Word":"lidandet","Syllables":["li","dan","det"]},{"Word":"lider","Syllables":["li","der"]},{"Word":"lika","Syllables":["li","ka"]},{"Word":"likadant","Syllables":["li","ka","dant"]},{"Word":"lisa","Syllables":["li","sa"]},{"Word":"lite","Syllables":["li","te"]},{"Word":"liten","Syllables":["li","ten"]},{"Word":"livet","Syllables":["li","vet"]},{"Word":"livets","Syllables":["li","ve","ts"]},{"Word":"ljusnar","Syllables":["ljus","nar"]},{"Word":"ljusen","Syllables":["lju","sen"]},{"Word":"ljuset","Syllables":["lju","set"]},{"Word":"ljusår","Syllables":["lju","sår"]},{"Word":"ljuva","Syllables":["lju","va"]},{"Word":"lockar","Syllables":["lock","ar"]},{"Word":"logga","Syllables":["log","ga"]},{"Word":"loppan","Syllables":["lop","pan"]},{"Word":"lotta","Syllables":["lot","ta"]},{"Word":"lokalisera","Syllables":["lo","ka","li","se","ra"]},{"Word":"luften","Syllables":["luf","ten"]},{"Word":"luktar","Syllables":["luk","tar"]},{"Word":"lurat","Syllables":["lu","rat"]},{"Word":"lyckan","Syllables":["lyck","an"]},{"Word":"lyckas","Syllables":["lyck","as"]},{"Word":"lyckats","Syllables":["lyck","ats"]},{"Word":"lycklig","Syllables":["lyck","lig"]},{"Word":"lyckligt","Syllables":["lyck","ligt"]},{"Word":"lyckliga","Syllables":["lyck","li","ga"]},{"Word":"lyfter","Syllables":["lyf","ter"]},{"Word":"lyssna","Syllables":["lys","sna"]},{"Word":"lyssnar","Syllables":["lys","snar"]},{"Word":"lyssnat","Syllables":["lys","snat"]},{"Word":"lyste","Syllables":["lys","te"]},{"Word":"lyder","Syllables":["ly","der"]},{"Word":"lägger","Syllables":["läg","ger"]},{"Word":"lämna","Syllables":["läm","na"]},{"Word":"lämnar","Syllables":["läm","nar"]},{"Word":"lämnat","Syllables":["läm","nat"]},{"Word":"länge","Syllables":["läng","e"]},{"Word":"längesen","Syllables":["läng","e","sen"]},{"Word":"längre","Syllables":["läng","re"]},{"Word":"längtan","Syllables":["läng","tan"]},{"Word":"längtar","Syllables":["läng","tar"]},{"Word":"längtat","Syllables":["läng","tat"]},{"Word":"längtade","Syllables":["läng","ta","de"]},{"Word":"läppar","Syllables":["läp","par"]},{"Word":"läppars","Syllables":["läp","pars"]},{"Word":"lärde","Syllables":["lär","de"]},{"Word":"lättar","Syllables":["lät","tar"]},{"Word":"läger","Syllables":["lä","ger"]},{"Word":"läkare","Syllables":["lä","ka","re"]},{"Word":"lära","Syllables":["lä","ra"]},{"Word":"läsa","Syllables":["lä","sa"]},{"Word":"läser","Syllables":["lä","ser"]},{"Word":"lådbil","Syllables":["låd","bil"]},{"Word":"lågtryck","Syllables":["låg","tryck"]},{"Word":"långgatanflickorna","Syllables":["lång","ga","tan","flick","or","na"]},{"Word":"långsam","Syllables":["lång","sam"]},{"Word":"långstrump","Syllables":["lång","strump"]},{"Word":"låsta","Syllables":["lås","ta"]},{"Word":"låda","Syllables":["lå","da"]},{"Word":"låga","Syllables":["lå","ga"]},{"Word":"lånar","Syllables":["lå","nar"]},{"Word":"låta","Syllables":["lå","ta"]},{"Word":"låten","Syllables":["lå","ten"]},{"Word":"låtens","Syllables":["lå","tens"]},{"Word":"låter","Syllables":["lå","ter"]},{"Word":"låtit","Syllables":["lå","tit"]},{"Word":"löften","Syllables":["löf","ten"]},{"Word":"lördag","Syllables":["lör","dag"]},{"Word":"lösning","Syllables":["lös","ning"]},{"Word":"lösa","Syllables":["lö","sa"]},{"Word":"löven","Syllables":["lö","ven"]},{"Word":"magnet","Syllables":["mag","net"]},{"Word":"mamma","Syllables":["mam","ma"]},{"Word":"mammor","Syllables":["mam","mor"]},{"Word":"mangfärgade","Syllables":["mang","fär","ga","de"]},{"Word":"mannelig","Syllables":["man","ne","lig"]},{"Word":"marknad","Syllables":["mark","nad"]},{"Word":"maskin","Syllables":["mask","in"]},{"Word":"maskrosblad","Syllables":["mask","ros","blad"]},{"Word":"massa","Syllables":["mas","sa"]},{"Word":"maste","Syllables":["mas","te"]},{"Word":"matchen","Syllables":["match","en"]},{"Word":"mage","Syllables":["ma","ge"]},{"Word":"magen","Syllables":["ma","gen"]},{"Word":"magi","Syllables":["ma","gi"]},{"Word":"malou","Syllables":["ma","lou"]},{"Word":"mare","Syllables":["ma","re"]},{"Word":"mareld","Syllables":["ma","reld"]},{"Word":"mary","Syllables":["ma","ry"]},{"Word":"maten","Syllables":["ma","ten"]},{"Word":"matematik","Syllables":["ma","te","ma","tik"]},{"Word":"materia","Syllables":["ma","te","ri","a"]},{"Word":"materialet","Syllables":["ma","te","ri","a","let"]},{"Word":"meddelande","Syllables":["med","de","lan","de"]},{"Word":"mellan","Syllables":["mel","lan"]},{"Word":"menfattar","Syllables":["men","fat","tar"]},{"Word":"menlösa","Syllables":["men","lö","sa"]},{"Word":"mercan","Syllables":["mer","can"]},{"Word":"mesta","Syllables":["mes","ta"]},{"Word":"medan","Syllables":["me","dan"]},{"Word":"medans","Syllables":["me","dans"]},{"Word":"melodi","Syllables":["me","lo","di"]},{"Word":"melodifestivalen","Syllables":["me","lo","di","fes","ti","va","len"]},{"Word":"mena","Syllables":["me","na"]},{"Word":"menar","Syllables":["me","nar"]},{"Word":"mena’","Syllables":["me","na’"]},{"Word":"menageri","Syllables":["me","na","ge","ri"]},{"Word":"meningslöst","Syllables":["me","nings","löst"]},{"Word":"meningslösa","Syllables":["me","nings","lö","sa"]},{"Word":"meningen","Syllables":["me","ning","en"]},{"Word":"mera","Syllables":["me","ra"]},{"Word":"metall","Syllables":["me","tall"]},{"Word":"metod","Syllables":["me","tod"]},{"Word":"middagstid","Syllables":["mid","dags","tid"]},{"Word":"midnatt","Syllables":["mid","natt"]},{"Word":"miljarder","Syllables":["mil","jar","der"]},{"Word":"miljoner","Syllables":["mil","jo","ner"]},{"Word":"mindre","Syllables":["min","dre"]},{"Word":"minnas","Syllables":["min","nas"]},{"Word":"minne","Syllables":["min","ne"]},{"Word":"minnen","Syllables":["min","nen"]},{"Word":"minnesnyckel","Syllables":["min","nes","nyck","el"]},{"Word":"minsta","Syllables":["min","sta"]},{"Word":"misslyckades","Syllables":["miss","lyck","a","des"]},{"Word":"misstänksam","Syllables":["miss","tänk","sam"]},{"Word":"missa","Syllables":["mis","sa"]},{"Word":"mistat","Syllables":["mis","tat"]},{"Word":"mittsista","Syllables":["mitt","sis","ta"]},{"Word":"mitten","Syllables":["mit","ten"]},{"Word":"michael","Syllables":["mi","cha","el"]},{"Word":"michelangelo","Syllables":["mi","che","lan","ge","lo"]},{"Word":"mina","Syllables":["mi","na"]},{"Word":"minut","Syllables":["mi","nut"]},{"Word":"miraklet","Syllables":["mi","rak","let"]},{"Word":"mjuka","Syllables":["mju","ka"]},{"Word":"monster","Syllables":["mon","ster"]},{"Word":"morsan","Syllables":["mors","an"]},{"Word":"morse","Syllables":["mors","e"]},{"Word":"morgon","Syllables":["mor","gon"]},{"Word":"morgonen","Syllables":["mor","go","nen"]},{"Word":"mossen","Syllables":["mos","sen"]},{"Word":"moster","Syllables":["mos","ter"]},{"Word":"motsatt","Syllables":["mot","satt"]},{"Word":"motståndets","Syllables":["mot","stån","dets"]},{"Word":"motta","Syllables":["mot","ta"]},{"Word":"moderna","Syllables":["mo","der","na"]},{"Word":"molekyl","Syllables":["mo","le","kyl"]},{"Word":"mona","Syllables":["mo","na"]},{"Word":"motiv","Syllables":["mo","tiv"]},{"Word":"motor","Syllables":["mo","tor"]},{"Word":"mullig","Syllables":["mul","lig"]},{"Word":"mulnar","Syllables":["mul","nar"]},{"Word":"multiplicera","Syllables":["mul","ti","pli","ce","ra"]},{"Word":"multiplikation","Syllables":["mul","ti","pli","ka","tion"]},{"Word":"munmotmunmetoden","Syllables":["mun","mot","mun","me","to","den"]},{"Word":"munnen","Syllables":["mun","nen"]},{"Word":"muren","Syllables":["mu","ren"]},{"Word":"musik","Syllables":["mu","sik"]},{"Word":"mycket","Syllables":["myck","et"]},{"Word":"mystik","Syllables":["mys","tik"]},{"Word":"männen","Syllables":["män","nen"]},{"Word":"människa","Syllables":["män","nisk","a"]},{"Word":"människor","Syllables":["män","nisk","or"]},{"Word":"människor","Syllables":["män","ni","skor"]},{"Word":"mänskor","Syllables":["män","skor"]},{"Word":"män’skor","Syllables":["män","’skor"]},{"Word":"märke","Syllables":["mär","ke"]},{"Word":"märker","Syllables":["mär","ker"]},{"Word":"mästare","Syllables":["mäs","ta","re"]},{"Word":"mästaren","Syllables":["mäs","ta","ren"]},{"Word":"mäta","Syllables":["mä","ta"]},{"Word":"många","Syllables":["mång","a"]},{"Word":"måndag","Syllables":["mån","dag"]},{"Word":"måntro","Syllables":["mån","tro"]},{"Word":"måste","Syllables":["mås","te"]},{"Word":"måla","Syllables":["må","la"]},{"Word":"månad","Syllables":["må","nad"]},{"Word":"månen","Syllables":["må","nen"]},{"Word":"måsarnas","Syllables":["må","sar","nas"]},{"Word":"möbler","Syllables":["möb","ler"]},{"Word":"möjlig","Syllables":["möj","lig"]},{"Word":"mönster","Syllables":["mön","ster"]},{"Word":"mörkret","Syllables":["mörk","ret"]},{"Word":"mörka","Syllables":["mör","ka"]},{"Word":"mörker","Syllables":["mör","ker"]},{"Word":"mötte","Syllables":["möt","te"]},{"Word":"möter","Syllables":["mö","ter"]},{"Word":"nalkas","Syllables":["nal","kas"]},{"Word":"nattgaraget","Syllables":["natt","ga","ra","get"]},{"Word":"natta","Syllables":["nat","ta"]},{"Word":"natten","Syllables":["nat","ten"]},{"Word":"nation","Syllables":["na","tion"]},{"Word":"natur","Syllables":["na","tur"]},{"Word":"naturlig","Syllables":["na","tur","lig"]},{"Word":"naturligt","Syllables":["na","tur","ligt"]},{"Word":"Naturligtvis","Syllables":["Na","tur","ligt","vis"]},{"Word":"neckens","Syllables":["neck","ens"]},{"Word":"nedsläckt","Syllables":["ned","släckt"]},{"Word":"nerför","Syllables":["ner","för"]},{"Word":"neon","Syllables":["ne","on"]},{"Word":"neongrön","Syllables":["ne","on","grön"]},{"Word":"nere","Syllables":["ne","re"]},{"Word":"nilsson","Syllables":["nils","son"]},{"Word":"nio","Syllables":["ni","o"]},{"Word":"nivå","Syllables":["ni","vå"]},{"Word":"noglärt","Syllables":["nog","lärt"]},{"Word":"nolltid","Syllables":["noll","tid"]},{"Word":"nollad","Syllables":["nol","lad"]},{"Word":"norden","Syllables":["nor","den"]},{"Word":"nostalgisk","Syllables":["nos","tal","gisk"]},{"Word":"nummer","Syllables":["num","mer"]},{"Word":"nuge","Syllables":["nu","ge"]},{"Word":"nunär","Syllables":["nu","när"]},{"Word":"nuringer","Syllables":["nu","ring","er"]},{"Word":"nyckel","Syllables":["nyck","el"]},{"Word":"nyttja’","Syllables":["nytt","ja’"]},{"Word":"nya","Syllables":["ny","a"]},{"Word":"nye","Syllables":["ny","e"]},{"Word":"nyfiken","Syllables":["ny","fi","ken"]},{"Word":"nyvunna","Syllables":["ny","vun","na"]},{"Word":"närmare","Syllables":["när","ma","re"]},{"Word":"nästan","Syllables":["näs","tan"]},{"Word":"nära","Syllables":["nä","ra"]},{"Word":"näsa","Syllables":["nä","sa"]},{"Word":"näsan","Syllables":["nä","san"]},{"Word":"nästa","Syllables":["nä","sta"]},{"Word":"några","Syllables":["någ","ra"]},{"Word":"nånsin","Syllables":["nån","sin"]},{"Word":"nånstans","Syllables":["nån","stans"]},{"Word":"nånting","Syllables":["nån","ting"]},{"Word":"nån’ting","Syllables":["nån","’ting"]},{"Word":"nå’nting","Syllables":["nå’n","ting"]},{"Word":"någon","Syllables":["nå","gon"]},{"Word":"någons","Syllables":["nå","gons"]},{"Word":"någonsin","Syllables":["nå","gon","sin"]},{"Word":"någonstans","Syllables":["nå","gon","stans"]},{"Word":"någonting","Syllables":["nå","gon","ting"]},{"Word":"något","Syllables":["nå","got"]},{"Word":"nålar","Syllables":["nå","lar"]},{"Word":"nödvändig","Syllables":["nöd","vän","dig"]},{"Word":"nötskal","Syllables":["nöt","skal"]},{"Word":"nöjer","Syllables":["nö","jer"]},{"Word":"objektet","Syllables":["ob","jek","tet"]},{"Word":"observera","Syllables":["ob","ser","ve","ra"]},{"Word":"också","Syllables":["ock","så"]},{"Word":"offer","Syllables":["of","fer"]},{"Word":"ofta","Syllables":["of","ta"]},{"Word":"olja","Syllables":["ol","ja"]},{"Word":"ombord","Syllables":["om","bord"]},{"Word":"omfamnad","Syllables":["om","fam","nad"]},{"Word":"omges","Syllables":["om","ges"]},{"Word":"omkring","Syllables":["om","kring"]},{"Word":"område","Syllables":["om","rå","de"]},{"Word":"ondska","Syllables":["ond","ska"]},{"Word":"ooa","Syllables":["oo","a"]},{"Word":"ordbok","Syllables":["ord","bok"]},{"Word":"ordnat","Syllables":["ord","nat"]},{"Word":"orden","Syllables":["or","den"]},{"Word":"ordentlig","Syllables":["or","dent","lig"]},{"Word":"order","Syllables":["or","der"]},{"Word":"ordna","Syllables":["or","dna"]},{"Word":"organ","Syllables":["or","gan"]},{"Word":"orkan","Syllables":["or","kan"]},{"Word":"orkar","Syllables":["or","kar"]},{"Word":"orsak","Syllables":["or","sak"]},{"Word":"oaaaa","Syllables":["o","aaaa"]},{"Word":"obekvämt","Syllables":["o","be","kvämt"]},{"Word":"obrukbara","Syllables":["o","bruk","ba","ra"]},{"Word":"ocean","Syllables":["o","ce","an"]},{"Word":"odjur","Syllables":["o","djur"]},{"Word":"oinspirerad","Syllables":["o","in","spi","re","rad"]},{"Word":"okej","Syllables":["o","kej"]},{"Word":"okänd","Syllables":["o","känd"]},{"Word":"olalala","Syllables":["o","la","la","la"]},{"Word":"omedelbar","Syllables":["o","me","del","bar"]},{"Word":"omelett","Syllables":["o","me","lett"]},{"Word":"original","Syllables":["o","ri","gi","nal"]},{"Word":"orup","Syllables":["o","rup"]},{"Word":"otrolige","Syllables":["o","tro","li","ge"]},{"Word":"otur","Syllables":["o","tur"]},{"Word":"ovan","Syllables":["o","van"]},{"Word":"ovanför","Syllables":["o","van","för"]},{"Word":"oändligt","Syllables":["o","änd","ligt"]},{"Word":"pallar","Syllables":["pal","lar"]},{"Word":"pangpang","Syllables":["pang","pang"]},{"Word":"panna","Syllables":["pan","na"]},{"Word":"pannan","Syllables":["pan","nan"]},{"Word":"pappa","Syllables":["pap","pa"]},{"Word":"papper","Syllables":["pap","per"]},{"Word":"parti","Syllables":["par","ti"]},{"Word":"party","Syllables":["par","ty"]},{"Word":"passa","Syllables":["pas","sa"]},{"Word":"passera","Syllables":["pas","se","ra"]},{"Word":"passerar","Syllables":["pas","se","rar"]},{"Word":"passerat","Syllables":["pas","se","rat"]},{"Word":"passerade","Syllables":["pas","se","ra","de"]},{"Word":"palace","Syllables":["pa","lace"]},{"Word":"paret","Syllables":["pa","ret"]},{"Word":"paris","Syllables":["pa","ris"]},{"Word":"passa","Syllables":["pa","ssa"]},{"Word":"pengar","Syllables":["peng","ar"]},{"Word":"penning","Syllables":["pen","ning"]},{"Word":"permissionen","Syllables":["per","mis","sio","nen"]},{"Word":"pernilla","Syllables":["per","nil","la"]},{"Word":"persiska","Syllables":["per","si","ska"]},{"Word":"personen","Syllables":["per","so","nen"]},{"Word":"pekar","Syllables":["pe","kar"]},{"Word":"period","Syllables":["pe","ri","od"]},{"Word":"peru","Syllables":["pe","ru"]},{"Word":"piller","Syllables":["pil","ler"]},{"Word":"pinne","Syllables":["pin","ne"]},{"Word":"pippi","Syllables":["pip","pi"]},{"Word":"pistol","Syllables":["pis","tol"]},{"Word":"pistolen","Syllables":["pis","to","len"]},{"Word":"pizza","Syllables":["piz","za"]},{"Word":"pianot","Syllables":["pi","a","not"]},{"Word":"platsen","Syllables":["plat","sen"]},{"Word":"planen","Syllables":["pla","nen"]},{"Word":"planer","Syllables":["pla","ner"]},{"Word":"planet","Syllables":["pla","net"]},{"Word":"plocka","Syllables":["plock","a"]},{"Word":"plockas","Syllables":["plock","as"]},{"Word":"plural","Syllables":["plu","ral"]},{"Word":"plötsligt","Syllables":["plöts","ligt"]},{"Word":"plötslig","Syllables":["plöt","slig"]},{"Word":"pojke","Syllables":["poj","ke"]},{"Word":"pojken","Syllables":["poj","ken"]},{"Word":"pollock","Syllables":["pol","lock"]},{"Word":"portarna","Syllables":["por","tar","na"]},{"Word":"portion","Syllables":["por","tion"]},{"Word":"polack","Syllables":["po","lack"]},{"Word":"populär","Syllables":["po","pu","lär"]},{"Word":"pose","Syllables":["po","se"]},{"Word":"poäng","Syllables":["po","äng"]},{"Word":"praktiken","Syllables":["prak","ti","ken"]},{"Word":"presskåta","Syllables":["press","kå","ta"]},{"Word":"pressen","Syllables":["pres","sen"]},{"Word":"precis","Syllables":["pre","cis"]},{"Word":"premiär","Syllables":["pre","mi","är"]},{"Word":"prinsessan","Syllables":["prin","ses","san"]},{"Word":"priset","Syllables":["pri","set"]},{"Word":"problem","Syllables":["prob","lem"]},{"Word":"problemet","Syllables":["pro","blem","et"]},{"Word":"processen","Syllables":["pro","ces","sen"]},{"Word":"produkt","Syllables":["pro","dukt"]},{"Word":"producera","Syllables":["pro","du","ce","ra"]},{"Word":"profil","Syllables":["pro","fil"]},{"Word":"prålig","Syllables":["prå","lig"]},{"Word":"publik","Syllables":["pub","lik"]},{"Word":"publiken","Syllables":["pub","li","ken"]},{"Word":"pudrad","Syllables":["pud","rad"]},{"Word":"pulsen","Syllables":["pul","sen"]},{"Word":"publiken","Syllables":["pu","bli","ken"]},{"Word":"påskliljorna","Syllables":["påsk","lil","jor","na"]},{"Word":"påfåglar","Syllables":["på","fåg","lar"]},{"Word":"qvinna","Syllables":["qvin","na"]},{"Word":"raffset","Syllables":["raff","set"]},{"Word":"rastlös","Syllables":["rast","lös"]},{"Word":"rasten","Syllables":["ras","ten"]},{"Word":"razzia","Syllables":["raz","zi","a"]},{"Word":"racet","Syllables":["ra","cet"]},{"Word":"raden","Syllables":["ra","den"]},{"Word":"rader","Syllables":["ra","der"]},{"Word":"radio","Syllables":["ra","di","o"]},{"Word":"radion","Syllables":["ra","di","on"]},{"Word":"radiobrus","Syllables":["ra","di","o","brus"]},{"Word":"rationell","Syllables":["ra","tio","nell"]},{"Word":"ready","Syllables":["rea","dy"]},{"Word":"regna","Syllables":["regn","a"]},{"Word":"regnet","Syllables":["regn","et"]},{"Word":"regnigt","Syllables":["regn","igt"]},{"Word":"regnskur","Syllables":["regn","skur"]},{"Word":"reste","Syllables":["res","te"]},{"Word":"resten","Syllables":["res","ten"]},{"Word":"redan","Syllables":["re","dan"]},{"Word":"redo","Syllables":["re","do"]},{"Word":"refräng","Syllables":["re","fräng"]},{"Word":"regel","Syllables":["re","gel"]},{"Word":"regent","Syllables":["re","gent"]},{"Word":"regera","Syllables":["re","ge","ra"]},{"Word":"register","Syllables":["re","gis","ter"]},{"Word":"region","Syllables":["re","gi","on"]},{"Word":"repetition","Syllables":["re","pe","ti","tion"]},{"Word":"repor","Syllables":["re","por"]},{"Word":"representerar","Syllables":["re","pre","sen","te","rar"]},{"Word":"resa","Syllables":["re","sa"]},{"Word":"resan","Syllables":["re","san"]},{"Word":"reser","Syllables":["re","ser"]},{"Word":"resor","Syllables":["re","sor"]},{"Word":"resultat","Syllables":["re","sul","tat"]},{"Word":"retat","Syllables":["re","tat"]},{"Word":"riktning","Syllables":["rikt","ning"]},{"Word":"riktigt","Syllables":["rik","tigt"]},{"Word":"ringde","Syllables":["ring","de"]},{"Word":"ringer","Syllables":["ring","er"]},{"Word":"rinna","Syllables":["rin","na"]},{"Word":"rinner","Syllables":["rin","ner"]},{"Word":"risken","Syllables":["ris","ken"]},{"Word":"riskera","Syllables":["ris","ke","ra"]},{"Word":"rister","Syllables":["ris","ter"]},{"Word":"ridande","Syllables":["ri","dan","de"]},{"Word":"ridån","Syllables":["ri","dån"]},{"Word":"rika","Syllables":["ri","ka"]},{"Word":"rita","Syllables":["ri","ta"]},{"Word":"river","Syllables":["ri","ver"]},{"Word":"rock’n’roll","Syllables":["rock","’n’","roll"]},{"Word":"robin","Syllables":["ro","bin"]},{"Word":"roger","Syllables":["ro","ger"]},{"Word":"rolig","Syllables":["ro","lig"]},{"Word":"roligt","Syllables":["ro","ligt"]},{"Word":"ropa","Syllables":["ro","pa"]},{"Word":"ropar","Syllables":["ro","par"]},{"Word":"rosendelunde","Syllables":["ro","sen","de","lun","de"]},{"Word":"roten","Syllables":["ro","ten"]},{"Word":"rullband","Syllables":["rull","band"]},{"Word":"rullar","Syllables":["rul","lar"]},{"Word":"rulle","Syllables":["rul","le"]},{"Word":"runtom","Syllables":["run","tom"]},{"Word":"rusar","Syllables":["ru","sar"]},{"Word":"ruvar","Syllables":["ru","var"]},{"Word":"ryggar","Syllables":["ryg","gar"]},{"Word":"rymden","Syllables":["rym","den"]},{"Word":"rymma","Syllables":["rym","ma"]},{"Word":"räcka","Syllables":["räck","a"]},{"Word":"räcker","Syllables":["räck","er"]},{"Word":"räddad","Syllables":["räd","dad"]},{"Word":"rädsla","Syllables":["räd","sla"]},{"Word":"rädslan","Syllables":["räd","slan"]},{"Word":"rädslor","Syllables":["räd","slor"]},{"Word":"räkna","Syllables":["räk","na"]},{"Word":"rättvisa","Syllables":["rätt","vi","sa"]},{"Word":"rätta","Syllables":["rät","ta"]},{"Word":"rätte","Syllables":["rät","te"]},{"Word":"råbiff","Syllables":["rå","biff"]},{"Word":"råkar","Syllables":["rå","kar"]},{"Word":"röksignaler","Syllables":["rök","sig","na","ler"]},{"Word":"rörde","Syllables":["rör","de"]},{"Word":"röjer","Syllables":["rö","jer"]},{"Word":"rörelse","Syllables":["rö","rel","se"]},{"Word":"röret","Syllables":["rö","ret"]},{"Word":"rma","Syllables":["r","ma"]},{"Word":"sabba","Syllables":["sab","ba"]},{"Word":"saknad","Syllables":["sak","nad"]},{"Word":"saknar","Syllables":["sak","nar"]},{"Word":"saknat","Syllables":["sak","nat"]},{"Word":"saknaden","Syllables":["sak","na","den"]},{"Word":"sakta","Syllables":["sak","ta"]},{"Word":"samla","Syllables":["sam","la"]},{"Word":"samlar","Syllables":["sam","lar"]},{"Word":"samma","Syllables":["sam","ma"]},{"Word":"sammans","Syllables":["sam","mans"]},{"Word":"sammanfattning","Syllables":["sam","man","fatt","ning"]},{"Word":"samtal","Syllables":["sam","tal"]},{"Word":"samtid","Syllables":["sam","tid"]},{"Word":"sanden","Syllables":["san","den"]},{"Word":"sanning","Syllables":["san","ning"]},{"Word":"sarja","Syllables":["sar","ja"]},{"Word":"satte","Syllables":["sat","te"]},{"Word":"saxofon","Syllables":["sax","o","fon"]},{"Word":"sagolika","Syllables":["sa","go","li","ka"]},{"Word":"sakerna","Syllables":["sa","ker","na"]},{"Word":"salam","Syllables":["sa","lam"]},{"Word":"salut","Syllables":["sa","lut"]},{"Word":"satan","Syllables":["sa","tan"]},{"Word":"satellit","Syllables":["sa","tel","lit"]},{"Word":"schlagern","Syllables":["schla","gern"]},{"Word":"schlagerdebut","Syllables":["schla","ger","de","but"]},{"Word":"schlgerfinalen","Syllables":["schl","ger","fi","na","len"]},{"Word":"segment","Syllables":["seg","ment"]},{"Word":"seilitz","Syllables":["sei","litz"]},{"Word":"sektion","Syllables":["sek","tion"]},{"Word":"sensation","Syllables":["sen","sa","tion"]},{"Word":"sexton","Syllables":["sex","ton"]},{"Word":"seattle","Syllables":["se","at","tle"]},{"Word":"sedan","Syllables":["se","dan"]},{"Word":"sedimentera","Syllables":["se","di","men","te","ra"]},{"Word":"segel","Syllables":["se","gel"]},{"Word":"sekund","Syllables":["se","kund"]},{"Word":"sekunder","Syllables":["se","kun","der"]},{"Word":"senare","Syllables":["se","na","re"]},{"Word":"separat","Syllables":["se","pa","rat"]},{"Word":"shelleys","Syllables":["shel","leys"]},{"Word":"shoppar","Syllables":["shop","par"]},{"Word":"showen","Syllables":["sho","wen"]},{"Word":"siffran","Syllables":["sif","fran"]},{"Word":"silver","Syllables":["sil","ver"]},{"Word":"simma","Syllables":["sim","ma"]},{"Word":"singel","Syllables":["sing","el"]},{"Word":"sinne","Syllables":["sin","ne"]},{"Word":"sista","Syllables":["sis","ta"]},{"Word":"sitta","Syllables":["sit","ta"]},{"Word":"sitter","Syllables":["sit","ter"]},{"Word":"sida","Syllables":["si","da"]},{"Word":"sidan","Syllables":["si","dan"]},{"Word":"sina","Syllables":["si","na"]},{"Word":"sion","Syllables":["si","on"]},{"Word":"situation","Syllables":["si","tu","a","tion"]},{"Word":"sjukdomen","Syllables":["sjuk","do","men"]},{"Word":"sjunga","Syllables":["sjung","a"]},{"Word":"sjunger","Syllables":["sjung","er"]},{"Word":"sjunker","Syllables":["sjun","ker"]},{"Word":"självförtroende","Syllables":["själv","för","tro","en","de"]},{"Word":"självmord","Syllables":["själv","mord"]},{"Word":"själva","Syllables":["själ","va"]},{"Word":"själen","Syllables":["sjä","len"]},{"Word":"skaffat","Syllables":["skaf","fat"]},{"Word":"skanstull","Syllables":["skans","tull"]},{"Word":"skanstullskväll","Syllables":["skans","tulls","kväll"]},{"Word":"skandalen","Syllables":["skan","da","len"]},{"Word":"skadar","Syllables":["ska","dar"]},{"Word":"skaka","Syllables":["ska","ka"]},{"Word":"skakad","Syllables":["ska","kad"]},{"Word":"skala","Syllables":["ska","la"]},{"Word":"skapa","Syllables":["ska","pa"]},{"Word":"skaren","Syllables":["ska","ren"]},{"Word":"skelett","Syllables":["ske","lett"]},{"Word":"skena","Syllables":["ske","na"]},{"Word":"skicka","Syllables":["skick","a"]},{"Word":"skickat","Syllables":["skick","at"]},{"Word":"skiftnyckel","Syllables":["skift","nyck","el"]},{"Word":"skildasätt","Syllables":["skil","da","sätt"]},{"Word":"skilja","Syllables":["skil","ja"]},{"Word":"skiljer","Syllables":["skil","jer"]},{"Word":"skingra","Syllables":["sking","ra"]},{"Word":"skjuter","Syllables":["skju","ter"]},{"Word":"skolgårdens","Syllables":["skol","går","dens"]},{"Word":"skogen","Syllables":["sko","gen"]},{"Word":"skojig","Syllables":["sko","jig"]},{"Word":"skola","Syllables":["sko","la"]},{"Word":"skrattande","Syllables":["skrat","tan","de"]},{"Word":"skrattar","Syllables":["skrat","tar"]},{"Word":"skrattas","Syllables":["skrat","tas"]},{"Word":"skrivbord","Syllables":["skriv","bord"]},{"Word":"skrika","Syllables":["skri","ka"]},{"Word":"skriker","Syllables":["skri","ker"]},{"Word":"skrikig","Syllables":["skri","kig"]},{"Word":"skriva","Syllables":["skri","va"]},{"Word":"skriven","Syllables":["skri","ven"]},{"Word":"skrivit","Syllables":["skri","vit"]},{"Word":"skräckslagen","Syllables":["skräck","sla","gen"]},{"Word":"skrämma","Syllables":["skräm","ma"]},{"Word":"skrämmer","Syllables":["skräm","mer"]},{"Word":"skuggornas","Syllables":["skug","gor","nas"]},{"Word":"skuldra","Syllables":["skul","dra"]},{"Word":"skulle","Syllables":["skul","le"]},{"Word":"skumbad","Syllables":["skum","bad"]},{"Word":"skurkar","Syllables":["skur","kar"]},{"Word":"skvallermagasin","Syllables":["skval","ler","ma","ga","sin"]},{"Word":"skydda","Syllables":["skyd","da"]},{"Word":"skylten","Syllables":["skyl","ten"]},{"Word":"skymmer","Syllables":["skym","mer"]},{"Word":"skymtar","Syllables":["skym","tar"]},{"Word":"skynda","Syllables":["skyn","da"]},{"Word":"skyndar","Syllables":["skyn","dar"]},{"Word":"skyar","Syllables":["sky","ar"]},{"Word":"skärpa","Syllables":["skär","pa"]},{"Word":"skåda","Syllables":["skå","da"]},{"Word":"skådisar","Syllables":["skå","di","sar"]},{"Word":"skålas","Syllables":["skå","las"]},{"Word":"skönhet","Syllables":["skön","het"]},{"Word":"slagsmål","Syllables":["slags","mål"]},{"Word":"slagträ","Syllables":["slag","trä"]},{"Word":"slagen","Syllables":["sla","gen"]},{"Word":"slagit","Syllables":["sla","git"]},{"Word":"slavarbetjänter","Syllables":["sla","var","be","tjän","ter"]},{"Word":"slitage","Syllables":["sli","tage"]},{"Word":"slussarnas","Syllables":["slus","sar","nas"]},{"Word":"slutlig","Syllables":["slut","lig"]},{"Word":"slutna","Syllables":["slut","na"]},{"Word":"sluta","Syllables":["slu","ta"]},{"Word":"slutar","Syllables":["slu","tar"]},{"Word":"slutat","Syllables":["slu","tat"]},{"Word":"sluter","Syllables":["slu","ter"]},{"Word":"släcktes","Syllables":["släck","tes"]},{"Word":"slängde","Syllables":["släng","de"]},{"Word":"slänger","Syllables":["släng","er"]},{"Word":"släppa","Syllables":["släp","pa"]},{"Word":"släpa’","Syllables":["slä","pa’"]},{"Word":"slösar","Syllables":["slö","sar"]},{"Word":"smarrig","Syllables":["smar","rig"]},{"Word":"smeka","Syllables":["sme","ka"]},{"Word":"smyger","Syllables":["smy","ger"]},{"Word":"smärtor","Syllables":["smär","tor"]},{"Word":"snabbaste","Syllables":["snab","bas","te"]},{"Word":"snacka","Syllables":["snack","a"]},{"Word":"snackas","Syllables":["snack","as"]},{"Word":"snarare","Syllables":["sna","ra","re"]},{"Word":"sniken","Syllables":["sni","ken"]},{"Word":"snubblar","Syllables":["snubb","lar"]},{"Word":"snyftare","Syllables":["snyf","ta","re"]},{"Word":"snyltar","Syllables":["snyl","tar"]},{"Word":"snälla","Syllables":["snäl","la"]},{"Word":"socker","Syllables":["sock","er"]},{"Word":"soffan","Syllables":["sof","fan"]},{"Word":"soldat","Syllables":["sol","dat"]},{"Word":"solglittrets","Syllables":["sol","glitt","rets"]},{"Word":"solsken","Syllables":["sol","sken"]},{"Word":"somarsnö","Syllables":["som","ar","snö"]},{"Word":"sommar","Syllables":["som","mar"]},{"Word":"sommar’n","Syllables":["som","mar’n"]},{"Word":"sommaren","Syllables":["som","ma","ren"]},{"Word":"somna’","Syllables":["som","na’"]},{"Word":"sorti","Syllables":["sor","ti"]},{"Word":"social","Syllables":["so","ci","al"]},{"Word":"sofia","Syllables":["so","fi","a"]},{"Word":"solade","Syllables":["so","la","de"]},{"Word":"solen","Syllables":["so","len"]},{"Word":"sova","Syllables":["so","va"]},{"Word":"sovande","Syllables":["so","van","de"]},{"Word":"sover","Syllables":["so","ver"]},{"Word":"sovit","Syllables":["so","vit"]},{"Word":"spammar","Syllables":["spam","mar"]},{"Word":"sparkar","Syllables":["spar","kar"]},{"Word":"spara","Syllables":["spa","ra"]},{"Word":"spendera","Syllables":["spen","de","ra"]},{"Word":"speciell","Syllables":["spe","ci","ell"]},{"Word":"speciellt","Syllables":["spe","ci","ellt"]},{"Word":"spegel","Syllables":["spe","gel"]},{"Word":"spela","Syllables":["spe","la"]},{"Word":"spelar","Syllables":["spe","lar"]},{"Word":"spillra","Syllables":["spill","ra"]},{"Word":"spilla","Syllables":["spil","la"]},{"Word":"spirar","Syllables":["spi","rar"]},{"Word":"spricka","Syllables":["sprick","a"]},{"Word":"spridning","Syllables":["sprid","ning"]},{"Word":"springa","Syllables":["spring","a"]},{"Word":"springer","Syllables":["spring","er"]},{"Word":"sprida","Syllables":["spri","da"]},{"Word":"spränger","Syllables":["spräng","er"]},{"Word":"spänningen","Syllables":["spän","ning","en"]},{"Word":"stackare","Syllables":["stack","a","re"]},{"Word":"stanna","Syllables":["stan","na"]},{"Word":"stannar","Syllables":["stan","nar"]},{"Word":"stanvill","Syllables":["stan","vill"]},{"Word":"starka","Syllables":["star","ka"]},{"Word":"staden","Syllables":["sta","den"]},{"Word":"stadens","Syllables":["sta","dens"]},{"Word":"stadigt","Syllables":["sta","digt"]},{"Word":"state","Syllables":["sta","te"]},{"Word":"station","Syllables":["sta","tion"]},{"Word":"stationen","Syllables":["sta","tio","nen"]},{"Word":"stava","Syllables":["sta","va"]},{"Word":"stavelse","Syllables":["sta","vel","se"]},{"Word":"stegen","Syllables":["ste","gen"]},{"Word":"sticker","Syllables":["stick","er"]},{"Word":"stilla","Syllables":["stil","la"]},{"Word":"stirrar","Syllables":["stir","rar"]},{"Word":"stiga","Syllables":["sti","ga"]},{"Word":"stiger","Syllables":["sti","ger"]},{"Word":"stjärna","Syllables":["stjär","na"]},{"Word":"stjärnor","Syllables":["stjär","nor"]},{"Word":"stjärnorna","Syllables":["stjär","nor","na"]},{"Word":"stockholm","Syllables":["stock","holm"]},{"Word":"stoppa","Syllables":["stop","pa"]},{"Word":"stoppar","Syllables":["stop","par"]},{"Word":"stormvind","Syllables":["storm","vind"]},{"Word":"storlek","Syllables":["stor","lek"]},{"Word":"stormar","Syllables":["stor","mar"]},{"Word":"stormen","Syllables":["stor","men"]},{"Word":"storsla","Syllables":["stor","sla"]},{"Word":"stora","Syllables":["sto","ra"]},{"Word":"stranden","Syllables":["stran","den"]},{"Word":"struntar","Syllables":["strun","tar"]},{"Word":"stryka","Syllables":["stry","ka"]},{"Word":"sträcka","Syllables":["sträck","a"]},{"Word":"sträcker","Syllables":["sträck","er"]},{"Word":"stråkkvartett","Syllables":["stråk","kvar","tett"]},{"Word":"strålar","Syllables":["strå","lar"]},{"Word":"strömmen","Syllables":["ström","men"]},{"Word":"stuckit","Syllables":["stuck","it"]},{"Word":"stunden","Syllables":["stun","den"]},{"Word":"stundersom","Syllables":["stun","der","som"]},{"Word":"studenten","Syllables":["stu","den","ten"]},{"Word":"studie","Syllables":["stu","di","e"]},{"Word":"stycke","Syllables":["styck","e"]},{"Word":"styckmord","Syllables":["styck","mord"]},{"Word":"styrka","Syllables":["styr","ka"]},{"Word":"styrkan","Syllables":["styr","kan"]},{"Word":"ställning","Syllables":["ställ","ning"]},{"Word":"ställer","Syllables":["stäl","ler"]},{"Word":"stämma","Syllables":["stäm","ma"]},{"Word":"stänga","Syllables":["stäng","a"]},{"Word":"stängda","Syllables":["stäng","da"]},{"Word":"stänkte","Syllables":["stänk","te"]},{"Word":"större","Syllables":["stör","re"]},{"Word":"störtar","Syllables":["stör","tar"]},{"Word":"stövlar","Syllables":["stöv","lar"]},{"Word":"substans","Syllables":["sub","stans"]},{"Word":"subtrahera","Syllables":["sub","tra","he","ra"]},{"Word":"suddats","Syllables":["sud","dats"]},{"Word":"suffixet","Syllables":["suf","fix","et"]},{"Word":"suttit","Syllables":["sut","tit"]},{"Word":"suger","Syllables":["su","ger"]},{"Word":"svallar","Syllables":["sval","lar"]},{"Word":"svara","Syllables":["sva","ra"]},{"Word":"svaren","Syllables":["sva","ren"]},{"Word":"svenskar","Syllables":["svens","kar"]},{"Word":"svettas","Syllables":["svet","tas"]},{"Word":"sverige","Syllables":["sve","ri","ge"]},{"Word":"svindel","Syllables":["svin","del"]},{"Word":"svävar","Syllables":["svä","var"]},{"Word":"svåra","Syllables":["svå","ra"]},{"Word":"sweden","Syllables":["swe","den"]},{"Word":"symbol","Syllables":["sym","bol"]},{"Word":"symtomen","Syllables":["sym","to","men"]},{"Word":"syntheseizergolven","Syllables":["syn","the","sei","zer","gol","ven"]},{"Word":"syrsor","Syllables":["syrs","or"]},{"Word":"syster","Syllables":["sys","ter"]},{"Word":"systemet","Syllables":["sys","te","met"]},{"Word":"systrar","Syllables":["sys","trar"]},{"Word":"synas","Syllables":["sy","nas"]},{"Word":"syre","Syllables":["sy","re"]},{"Word":"syret","Syllables":["sy","ret"]},{"Word":"sälja","Syllables":["säl","ja"]},{"Word":"sällan","Syllables":["säl","lan"]},{"Word":"sämsta","Syllables":["säm","sta"]},{"Word":"sändningstid","Syllables":["sänd","nings","tid"]},{"Word":"särskilt","Syllables":["sär","skilt"]},{"Word":"sätta","Syllables":["sät","ta"]},{"Word":"sätter","Syllables":["sät","ter"]},{"Word":"säga","Syllables":["sä","ga"]},{"Word":"säger","Syllables":["sä","ger"]},{"Word":"säker","Syllables":["sä","ker"]},{"Word":"säkert","Syllables":["sä","kert"]},{"Word":"säsong","Syllables":["sä","song"]},{"Word":"säte","Syllables":["sä","te"]},{"Word":"sånna","Syllables":["sån","na"]},{"Word":"sådan","Syllables":["så","dan"]},{"Word":"sådär","Syllables":["så","där"]},{"Word":"sådära","Syllables":["så","dä","ra"]},{"Word":"sågen","Syllables":["så","gen"]},{"Word":"sålunda","Syllables":["så","lun","da"]},{"Word":"såont","Syllables":["så","ont"]},{"Word":"såren","Syllables":["så","ren"]},{"Word":"sökte","Syllables":["sök","te"]},{"Word":"söndag","Syllables":["sön","dag"]},{"Word":"söndags","Syllables":["sön","dags"]},{"Word":"sönder","Syllables":["sön","der"]},{"Word":"söder","Syllables":["sö","der"]},{"Word":"söta","Syllables":["sö","ta"]},{"Word":"tankar","Syllables":["tan","kar"]},{"Word":"tankarna","Syllables":["tan","kar","na"]},{"Word":"tanke","Syllables":["tan","ke"]},{"Word":"tanken","Syllables":["tan","ken"]},{"Word":"tappat","Syllables":["tap","pat"]},{"Word":"tavlor","Syllables":["tav","lor"]},{"Word":"tabell","Syllables":["ta","bell"]},{"Word":"tabu","Syllables":["ta","bu"]},{"Word":"taget","Syllables":["ta","get"]},{"Word":"tagit","Syllables":["ta","git"]},{"Word":"taken","Syllables":["ta","ken"]},{"Word":"taket","Syllables":["ta","ket"]},{"Word":"tala","Syllables":["ta","la"]},{"Word":"talar","Syllables":["ta","lar"]},{"Word":"talat","Syllables":["ta","lat"]},{"Word":"talade","Syllables":["ta","la","de"]},{"Word":"talet","Syllables":["ta","let"]},{"Word":"tecken","Syllables":["teck","en"]},{"Word":"temperatur","Syllables":["tem","pe","ra","tur"]},{"Word":"testet","Syllables":["tes","tet"]},{"Word":"teknikområdet","Syllables":["te","kni","kom","rå","det"]},{"Word":"telefon","Syllables":["te","le","fon"]},{"Word":"terapi","Syllables":["te","ra","pi"]},{"Word":"tigger","Syllables":["tig","ger"]},{"Word":"tillbaks","Syllables":["till","baks"]},{"Word":"tillbaka","Syllables":["till","ba","ka"]},{"Word":"tillhandahålla","Syllables":["till","han","da","hål","la"]},{"Word":"tillräckligt","Syllables":["till","räck","ligt"]},{"Word":"tillsammans","Syllables":["till","sam","mans"]},{"Word":"tillstånd","Syllables":["till","stånd"]},{"Word":"tillvaron","Syllables":["till","va","ron"]},{"Word":"tillåta","Syllables":["til","lå","ta"]},{"Word":"tiltad","Syllables":["til","tad"]},{"Word":"timme","Syllables":["tim","me"]},{"Word":"timmen","Syllables":["tim","men"]},{"Word":"tindrar","Syllables":["tind","rar"]},{"Word":"titta","Syllables":["tit","ta"]},{"Word":"tittar","Syllables":["tit","tar"]},{"Word":"tittade","Syllables":["tit","ta","de"]},{"Word":"tiden","Syllables":["ti","den"]},{"Word":"tider","Syllables":["ti","der"]},{"Word":"tidig","Syllables":["ti","dig"]},{"Word":"timo","Syllables":["ti","mo"]},{"Word":"titeln","Syllables":["ti","teln"]},{"Word":"tjejerna","Syllables":["tje","jer","na"]},{"Word":"tjejernas","Syllables":["tje","jer","nas"]},{"Word":"tjolahej","Syllables":["tjo","la","hej"]},{"Word":"tjolahopp","Syllables":["tjo","la","hopp"]},{"Word":"tjolahoppsansa","Syllables":["tjo","la","hopp","san","sa"]},{"Word":"tjugefyra","Syllables":["tju","ge","fy","ra"]},{"Word":"tjugo","Syllables":["tju","go"]},{"Word":"tjäna","Syllables":["tjä","na"]},{"Word":"tonhöjd","Syllables":["ton","höjd"]},{"Word":"toppklass","Syllables":["topp","klass"]},{"Word":"torka","Syllables":["tor","ka"]},{"Word":"torkat","Syllables":["tor","kat"]},{"Word":"torrare","Syllables":["tor","ra","re"]},{"Word":"toge","Syllables":["to","ge"]},{"Word":"totalt","Syllables":["to","talt"]},{"Word":"transport","Syllables":["tran","sport"]},{"Word":"trasigt","Syllables":["tra","sigt"]},{"Word":"trettinie","Syllables":["tret","ti","ni","e"]},{"Word":"tredje","Syllables":["tre","dje"]},{"Word":"triangel","Syllables":["tri","ang","el"]},{"Word":"trivas","Syllables":["tri","vas"]},{"Word":"trodde","Syllables":["trod","de"]},{"Word":"trolig","Syllables":["tro","lig"]},{"Word":"trumpet","Syllables":["trum","pet"]},{"Word":"trygga","Syllables":["tryg","ga"]},{"Word":"trädgård","Syllables":["träd","gård"]},{"Word":"trädgården","Syllables":["träd","går","den"]},{"Word":"träffar","Syllables":["träf","far"]},{"Word":"träffas","Syllables":["träf","fas"]},{"Word":"träffat","Syllables":["träf","fat"]},{"Word":"träffats","Syllables":["träf","fats"]},{"Word":"träden","Syllables":["trä","den"]},{"Word":"tråkigt","Syllables":["trå","kigt"]},{"Word":"trötta","Syllables":["tröt","ta"]},{"Word":"tunga","Syllables":["tung","a"]},{"Word":"tungan","Syllables":["tung","an"]},{"Word":"tunna","Syllables":["tun","na"]},{"Word":"turné","Syllables":["tur","né"]},{"Word":"tusen","Syllables":["tu","sen"]},{"Word":"tyckas","Syllables":["tyck","as"]},{"Word":"tycker","Syllables":["tyck","er"]},{"Word":"tystnad","Syllables":["tyst","nad"]},{"Word":"tystnar","Syllables":["tyst","nar"]},{"Word":"tyder","Syllables":["ty","der"]},{"Word":"tyrannen","Syllables":["ty","ran","nen"]},{"Word":"tyvärr","Syllables":["ty","värr"]},{"Word":"täcke","Syllables":["täck","e"]},{"Word":"tänkte","Syllables":["tänk","te"]},{"Word":"tänder","Syllables":["tän","der"]},{"Word":"tänderna","Syllables":["tän","der","na"]},{"Word":"tändes","Syllables":["tän","des"]},{"Word":"tänka","Syllables":["tän","ka"]},{"Word":"tänker","Syllables":["tän","ker"]},{"Word":"tätnar","Syllables":["tät","nar"]},{"Word":"tårta","Syllables":["tår","ta"]},{"Word":"tårarna","Syllables":["tå","rar","na"]},{"Word":"ugglor","Syllables":["ugg","lor"]},{"Word":"unga","Syllables":["ung","a"]},{"Word":"ungersven","Syllables":["ung","er","sven"]},{"Word":"undan","Syllables":["un","dan"]},{"Word":"under","Syllables":["un","der"]},{"Word":"underst","Syllables":["un","derst"]},{"Word":"underbar","Syllables":["un","der","bar"]},{"Word":"underlig","Syllables":["un","der","lig"]},{"Word":"underligt","Syllables":["un","der","ligt"]},{"Word":"undervisa","Syllables":["un","der","vi","sa"]},{"Word":"undra","Syllables":["un","dra"]},{"Word":"undrar","Syllables":["un","drar"]},{"Word":"uppfinna","Syllables":["upp","fin","na"]},{"Word":"uppgivna","Syllables":["upp","giv","na"]},{"Word":"upprann","Syllables":["upp","rann"]},{"Word":"upprepning","Syllables":["upp","rep","ning"]},{"Word":"uppsättning","Syllables":["upp","sätt","ning"]},{"Word":"upptagen","Syllables":["upp","ta","gen"]},{"Word":"upptäcker","Syllables":["upp","täck","er"]},{"Word":"upptäckte","Syllables":["upp","täck","te"]},{"Word":"ursäkt","Syllables":["ur","säkt"]},{"Word":"urval","Syllables":["ur","val"]},{"Word":"utför","Syllables":["ut","för"]},{"Word":"utnyttja","Syllables":["ut","nytt","ja"]},{"Word":"utsträckt","Syllables":["ut","sträckt"]},{"Word":"utveckla","Syllables":["ut","veck","la"]},{"Word":"uvhagen","Syllables":["uv","ha","gen"]},{"Word":"ufo","Syllables":["u","fo"]},{"Word":"utan","Syllables":["u","tan"]},{"Word":"utav","Syllables":["u","tav"]},{"Word":"uti","Syllables":["u","ti"]},{"Word":"utom","Syllables":["u","tom"]},{"Word":"utomjords","Syllables":["u","tom","jords"]},{"Word":"vacker","Syllables":["vack","er"]},{"Word":"vackert","Syllables":["vack","ert"]},{"Word":"vackra","Syllables":["vack","ra"]},{"Word":"vackraste","Syllables":["vack","ras","te"]},{"Word":"vagga","Syllables":["vag","ga"]},{"Word":"vakna","Syllables":["vak","na"]},{"Word":"vaknar","Syllables":["vak","nar"]},{"Word":"vaktar","Syllables":["vak","tar"]},{"Word":"vandrat","Syllables":["van","drat"]},{"Word":"vanlig","Syllables":["van","lig"]},{"Word":"vanligt","Syllables":["van","ligt"]},{"Word":"vardagens","Syllables":["var","da","gens"]},{"Word":"varför","Syllables":["var","för"]},{"Word":"vargar","Syllables":["var","gar"]},{"Word":"varje","Syllables":["var","je"]},{"Word":"varjedag","Syllables":["var","je","dag"]},{"Word":"vartenda","Syllables":["var","ten","da"]},{"Word":"vattnet","Syllables":["vatt","net"]},{"Word":"vatten","Syllables":["vat","ten"]},{"Word":"vattenspår","Syllables":["vat","ten","spår"]},{"Word":"vadå","Syllables":["va","då"]},{"Word":"vaken","Syllables":["va","ken"]},{"Word":"vara","Syllables":["va","ra"]},{"Word":"varann","Syllables":["va","rann"]},{"Word":"varandra","Syllables":["va","ran","dra"]},{"Word":"varenda","Syllables":["va","ren","da"]},{"Word":"varit","Syllables":["va","rit"]},{"Word":"varierar","Syllables":["va","ri","e","rar"]},{"Word":"vecka","Syllables":["veck","a"]},{"Word":"verklig","Syllables":["verk","lig"]},{"Word":"verkligt","Syllables":["verk","ligt"]},{"Word":"verktyg","Syllables":["verk","tyg"]},{"Word":"verka","Syllables":["ver","ka"]},{"Word":"verkar","Syllables":["ver","kar"]},{"Word":"verklighet","Syllables":["ver","klig","het"]},{"Word":"verkligen","Syllables":["ver","kli","gen"]},{"Word":"veta","Syllables":["ve","ta"]},{"Word":"vetenskap","Syllables":["ve","ten","skap"]},{"Word":"vetenskapligt","Syllables":["ve","ten","skap","ligt"]},{"Word":"vicka","Syllables":["vick","a"]},{"Word":"vidderna","Syllables":["vid","der","na"]},{"Word":"vilja","Syllables":["vil","ja"]},{"Word":"viljan","Syllables":["vil","jan"]},{"Word":"viljen","Syllables":["vil","jen"]},{"Word":"vilken","Syllables":["vil","ken"]},{"Word":"vilket","Syllables":["vil","ket"]},{"Word":"villa","Syllables":["vil","la"]},{"Word":"villan","Syllables":["vil","lan"]},{"Word":"ville","Syllables":["vil","le"]},{"Word":"villekulla","Syllables":["vil","le","kul","la"]},{"Word":"vilsen","Syllables":["vil","sen"]},{"Word":"vimlar","Syllables":["vim","lar"]},{"Word":"vingar","Syllables":["ving","ar"]},{"Word":"vinge","Syllables":["ving","e"]},{"Word":"vingla","Syllables":["ving","la"]},{"Word":"vindar","Syllables":["vin","dar"]},{"Word":"vindarna","Syllables":["vin","dar","na"]},{"Word":"vindarnas","Syllables":["vin","dar","nas"]},{"Word":"vinden","Syllables":["vin","den"]},{"Word":"vinkar","Syllables":["vin","kar"]},{"Word":"vinkeln","Syllables":["vin","keln"]},{"Word":"vinna","Syllables":["vin","na"]},{"Word":"vinnare","Syllables":["vin","na","re"]},{"Word":"vinner","Syllables":["vin","ner"]},{"Word":"vinter","Syllables":["vin","ter"]},{"Word":"vintern","Syllables":["vin","tern"]},{"Word":"vinterdrog","Syllables":["vin","ter","drog"]},{"Word":"viskning","Syllables":["visk","ning"]},{"Word":"visste","Syllables":["viss","te"]},{"Word":"vissa","Syllables":["vis","sa"]},{"Word":"visste","Syllables":["vis","ste"]},{"Word":"via","Syllables":["vi","a"]},{"Word":"vilar","Syllables":["vi","lar"]},{"Word":"viner","Syllables":["vi","ner"]},{"Word":"visa","Syllables":["vi","sa"]},{"Word":"visar","Syllables":["vi","sar"]},{"Word":"visas","Syllables":["vi","sas"]},{"Word":"visat","Syllables":["vi","sat"]},{"Word":"visa’","Syllables":["vi","sa’"]},{"Word":"visioner","Syllables":["vi","sio","ner"]},{"Word":"vita","Syllables":["vi","ta"]},{"Word":"vokal","Syllables":["vo","kal"]},{"Word":"vokalister","Syllables":["vo","ka","lis","ter"]},{"Word":"vore","Syllables":["vo","re"]},{"Word":"vrider","Syllables":["vri","der"]},{"Word":"vunnit","Syllables":["vun","nit"]},{"Word":"väldigt","Syllables":["väl","digt"]},{"Word":"välja","Syllables":["väl","ja"]},{"Word":"väller","Syllables":["väl","ler"]},{"Word":"välserverat","Syllables":["väl","ser","ve","rat"]},{"Word":"vändning","Syllables":["vänd","ning"]},{"Word":"vända","Syllables":["vän","da"]},{"Word":"vänder","Syllables":["vän","der"]},{"Word":"vänlig","Syllables":["vän","lig"]},{"Word":"vänligen","Syllables":["vän","li","gen"]},{"Word":"vännen","Syllables":["vän","nen"]},{"Word":"vänner","Syllables":["vän","ner"]},{"Word":"vänster","Syllables":["vän","ster"]},{"Word":"vänstrar","Syllables":["vän","strar"]},{"Word":"vänta","Syllables":["vän","ta"]},{"Word":"väntan","Syllables":["vän","tan"]},{"Word":"väntar","Syllables":["vän","tar"]},{"Word":"väntat","Syllables":["vän","tat"]},{"Word":"världen","Syllables":["värl","den"]},{"Word":"värsta","Syllables":["värs","ta"]},{"Word":"värde","Syllables":["vär","de"]},{"Word":"värme","Syllables":["vär","me"]},{"Word":"väskor","Syllables":["väs","kor"]},{"Word":"väster","Syllables":["väs","ter"]},{"Word":"vätska","Syllables":["vät","ska"]},{"Word":"vävda","Syllables":["väv","da"]},{"Word":"växa","Syllables":["väx","a"]},{"Word":"växer","Syllables":["väx","er"]},{"Word":"växte","Syllables":["väx","te"]},{"Word":"väder","Syllables":["vä","der"]},{"Word":"vägen","Syllables":["vä","gen"]},{"Word":"våldtäkt","Syllables":["våld","täkt"]},{"Word":"våga","Syllables":["vå","ga"]},{"Word":"vågar","Syllables":["vå","gar"]},{"Word":"vågat","Syllables":["vå","gat"]},{"Word":"våningssäng","Syllables":["vå","nings","säng"]},{"Word":"våningen","Syllables":["vå","ning","en"]},{"Word":"våra","Syllables":["vå","ra"]},{"Word":"våran","Syllables":["vå","ran"]},{"Word":"vårat","Syllables":["vå","rat"]},{"Word":"våta","Syllables":["vå","ta"]},{"Word":"werther","Syllables":["wer","ther"]},{"Word":"winners","Syllables":["win","ners"]},{"Word":"woopytoopy","Syllables":["woo","py","too","py"]},{"Word":"yeti","Syllables":["ye","ti"]},{"Word":"yxorna","Syllables":["yx","or","na"]},{"Word":"yta","Syllables":["y","ta"]},{"Word":"ytan","Syllables":["y","tan"]},{"Word":"älskling","Syllables":["äls","kling"]},{"Word":"älska","Syllables":["äl","ska"]},{"Word":"älskad","Syllables":["äl","skad"]},{"Word":"älskar","Syllables":["äl","skar"]},{"Word":"älskat","Syllables":["äl","skat"]},{"Word":"älskade","Syllables":["äl","ska","de"]},{"Word":"älvor","Syllables":["äl","vor"]},{"Word":"ämne","Syllables":["äm","ne"]},{"Word":"ändlös","Syllables":["änd","lös"]},{"Word":"ändrar","Syllables":["änd","rar"]},{"Word":"ängel","Syllables":["äng","el"]},{"Word":"änglar","Syllables":["äng","lar"]},{"Word":"änglarna","Syllables":["äng","lar","na"]},{"Word":"ända","Syllables":["än","da"]},{"Word":"ände","Syllables":["än","de"]},{"Word":"ändå","Syllables":["än","då"]},{"Word":"ännu","Syllables":["än","nu"]},{"Word":"äntligen","Syllables":["än","tli","gen"]},{"Word":"äpple","Syllables":["äpp","le"]},{"Word":"ärlig","Syllables":["ärl","ig"]},{"Word":"ärrena","Syllables":["är","re","na"]},{"Word":"äger","Syllables":["ä","ger"]},{"Word":"ägodel","Syllables":["ä","go","del"]},{"Word":"äta","Syllables":["ä","ta"]},{"Word":"äter","Syllables":["ä","ter"]},{"Word":"även","Syllables":["ä","ven"]},{"Word":"äventyra","Syllables":["ä","ven","ty","ra"]},{"Word":"åkte","Syllables":["åk","te"]},{"Word":"ånga","Syllables":["ång","a"]},{"Word":"årstider","Syllables":["års","ti","der"]},{"Word":"åtta","Syllables":["åt","ta"]},{"Word":"åker","Syllables":["å","ker"]},{"Word":"återvänder","Syllables":["å","ter","vän","der"]},{"Word":"öknen","Syllables":["ök","nen"]},{"Word":"ölkafé","Syllables":["öl","ka","fé"]},{"Word":"ömmar","Syllables":["öm","mar"]},{"Word":"önskar","Syllables":["ön","skar"]},{"Word":"önskade","Syllables":["ön","ska","de"]},{"Word":"öppna","Syllables":["öpp","na"]},{"Word":"öppnar","Syllables":["öpp","nar"]},{"Word":"öppen","Syllables":["öp","pen"]},{"Word":"öppenfamn","Syllables":["öp","pen","famn"]},{"Word":"öppet","Syllables":["öp","pet"]},{"Word":"övning","Syllables":["öv","ning"]},{"Word":"öde","Syllables":["ö","de"]},{"Word":"öga","Syllables":["ö","ga"]},{"Word":"ögon","Syllables":["ö","gon"]},{"Word":"ögonblick","Syllables":["ö","gon","blick"]},{"Word":"ögonens","Syllables":["ö","go","nens"]},{"Word":"öken","Syllables":["ö","ken"]},{"Word":"örat","Syllables":["ö","rat"]},{"Word":"öser","Syllables":["ö","ser"]},{"Word":"över","Syllables":["ö","ver"]},{"Word":"överallt","Syllables":["ö","ver","allt"]},{"Word":"överflöd","Syllables":["ö","ver","flöd"]},{"Word":"överlägset","Syllables":["ö","ver","läg","set"]},{"Word":"överraskning","Syllables":["ö","ver","rask","ning"]},{"Word":"övertygande","Syllables":["ö","ver","ty","gan","de"]},{"Word":"överväga","Syllables":["ö","ver","vä","ga"]}]